Workbook
Name NativeTimeline_Order_Date: #N/A
Name Slicer_Category: #N/A
Name Slicer_City: #N/A
Name Slicer_Customer_Status: #N/A
Name Slicer_Payment_Method: #N/A

Sheet Raw_Data
A1: Order_ID | B1: Customer_Name | C1: Email | D1: Phone | E1: City | F1: Product | G1: Category | H1: Order_Date | I1: Quantity | J1: Unit_Price | K1: Total_Sales | L1: Payment_Method | M1: Customer_Status | N1: Delivery_Date
A2: ORD-1001 | B2: Mahnoor Khan | C2: mahnoor.khan@yahoo.com | D2: 0369 2458591 | E2: Lahore | F2: Microwave Oven | H2: 46238 | I2: 2 | J2: 45000 | K2: =I2*J2 -> 90000 | L2: Cash | N2: 46243
A3: ORD-1002 | B3: Fahad Qureshi | C3: fahad.qureshi@yahoo.com | D3: 03482622631 | E3: Faisalabad | F3: Vacuum Cleaner | G3: Home Appliances | H3: 46244 | I3: 3 | J3: 85000 | K3: =I3*J3 -> 255000 | L3: Credit Card | M3: Active | N3: 46250
A4: ORD-1003 | B4: Waqas Ali | C4: waqas.ali@gmail.com | D4: 03207210606 | E4: FAISALABAD | F4: Headphones | G4: ELECTRONICS | H4: 46233 | I4: 3 | J4: 120000 | K4: =I4*J4 -> 360000 | L4: jazzcash | M4: ACTIVE | N4: 46238
A5: ORD-1004 | B5: Ayesha Iqbal | C5: AYESHA.IQBAL@HOTMAIL.COM | D5: 0372-6279418 | E5: PESHAWAR | F5: Bookshelf | G5: Furniture | H5: 46241 | I5: 5 | J5: 25000 | K5: =I5*J5 -> 125000 | L5: Bank Transfer | M5: active | N5: 46246
A6: ORD-1005 | B6: Zainab Ahmed | C6: zainab.ahmed@yahoo.com | D6: 03087455324 | E6: SIALKOT | F6: Vacuum Cleaner | G6: Home Appliances | H6: 46252 | I6: 3 | J6: 2500 | K6: =I6*J6 -> 7500 | L6: credit card | N6: 46256
A7: ORD-1006 | B7: Kashif Anwar | C7: kashif.anwar@gmail.com | D7: 0377-4337174 | E7: ISLAMABAD | F7: Microwave Oven | G7: Home Appliances | H7: 46227 | I7: 2 | J7: 1500 | K7: =I7*J7 -> 3000 | L7: Credit Card | M7: Active | N7: 46231
A8: ORD-1007 | B8: Bushra Ali | C8: bushra.ali@yahoo.com | D8: 0333 9852897 | E8: RAWALPINDI | F8: Study Table | G8: FURNITURE | H8: 46232 | I8: 4 | J8: 2500 | K8: =I8*J8 -> 10000 | L8: Credit Card | N8: 46238
A9: ORD-1008 | B9: Rida Iqbal | C9: rida.iqbal@gmail.com | D9: 0304-6543670 | E9: FAISALABAD | F9: Vacuum Cleaner | G9: Home Appliances | H9: 46219 | I9: 4 | J9: 8500 | K9: =I9*J9 -> 34000 | L9: cash | M9: Inactive | N9: 46224
A10: ORD-1009 | B10: Junaid Baig | C10: junaid.baig@gmail.com | D10: 0351-6692553 | E10: RAWALPINDI | F10: Sunglasses | G10: Accessories | H10: 46232 | I10: 1 | J10: 1500 | K10: =I10*J10 -> 1500 | L10: jazzcash | M10: Active | N10: 46238
A11: ORD-1010 | B11: Nida Sheikh | C11: nida.sheikh@outlook.com | D11: 03481036161 | E11: sialkot | F11: Vacuum Cleaner | G11: HOME APPLIANCES | H11: 46207 | I11: 5 | J11: 1500 | K11: =I11*J11 -> 7500 | L11: Bank Transfer | M11: inactive | N11: 46213
A12: ORD-1011 | B12: Anum Sheikh | C12: ANUM.SHEIKH@GMAIL.COM | D12: 0330-7774229 | E12: RAWALPINDI | F12: Water Dispenser | G12: Home Appliances | H12: 46220 | I12: 3 | J12: 8500 | K12: =I12*J12 -> 25500 | L12: credit card | M12: Pending | N12: 46223
A13: ORD-1012 | B13: Noor Farooq | C13: noor.farooq@gmail.com | D13: 0312 2229110 | E13: Faisalabad | F13: Headphones | G13: Electronics | H13: 46249 | I13: 5 | J13: 120000 | K13: =I13*J13 -> 600000 | M13: pending | N13: 46253
A14: ORD-1013 | B14: Usman Butt | C14: usman.butt@gmail.com | D14: 0326-6752576 | E14: FAISALABAD | F14: Mobile Phone | G14: Electronics | H14: 46225 | I14: 3 | J14: 4000 | K14: =I14*J14 -> 12000 | L14: JazzCash | M14: Inactive | N14: 46228
A15: ORD-1014 | B15: Mahnoor Ali | C15: mahnoor.ali@yahoo.com | E15: Multan | F15: Study Table | G15: FURNITURE | H15: 46230 | I15: 2 | J15: 8500 | K15: =I15*J15 -> 17000 | L15: CASH | M15: pending | N15: 46236
A16: ORD-1015 | B16: Junaid Khan | C16: junaid.khan@hotmail.com | D16: 03945163555 | E16: Karachi | F16: Blender | G16: Home Appliances | H16: 46254 | I16: 2 | J16: 1500 | K16: =I16*J16 -> 3000 | L16: Credit Card | M16: ACTIVE | N16: 46257
A17: ORD-1016 | B17: Rabia Javed | C17: rabia.javed@outlook.com | D17: 03032935113 | E17: Faisalabad | F17: Sunglasses | G17: accessories | H17: 46236 | I17: 4 | J17: 85000 | K17: =I17*J17 -> 340000 | L17: Credit Card | M17: Pending | N17: 46238
A18: ORD-1017 | B18: Anum Siddiqui | C18: ANUM.SIDDIQUI@YAHOO.COM | D18: 0342 6266630 | E18: FAISALABAD | F18: Sunglasses | G18: accessories | H18: 46230 | I18: 4 | J18: 120000 | K18: =I18*J18 -> 480000 | L18: CASH | M18: ACTIVE | N18: 46237
A19: ORD-1018 | B19: Ali Chaudhry | C19: ali.chaudhry@outlook.com | D19: 0356 8418210 | E19: SIALKOT | F19: Headphones | G19: electronics | H19: 46252 | I19: 3 | J19: 8500 | K19: =I19*J19 -> 25500 | L19: Credit Card | M19: Active | N19: 46255
A20: ORD-1019 | B20: Faisal Awan | C20: faisal.awan@gmail.com | D20: 03917442089 | E20: ISLAMABAD | F20: Smart Watch | G20: electronics | H20: 46233 | I20: 5 | J20: 8500 | K20: =I20*J20 -> 42500 | L20: cash | M20: pending | N20: 46235
A21: ORD-1020 | B21: Anum Siddiqui | C21: anum.siddiqui@outlook.com | D21: 0370-8481188 | E21: sialkot | F21: Sofa Set | G21: FURNITURE | H21: 46219 | I21: 4 | J21: 2500 | K21: =I21*J21 -> 10000 | L21: credit card | M21: ACTIVE | N21: 46223
A22: ORD-1021 | B22: Danish Ali | C22: danish.ali@yahoo.com | D22: 03537838382 | E22: Peshawar | F22: Sunglasses | G22: accessories | H22: 46252 | I22: 4 | J22: 45000 | K22: =I22*J22 -> 180000 | L22: Cash | M22: ACTIVE | N22: 46258
A23: ORD-1022 | B23: Junaid Siddiqui | C23: junaid.siddiqui@yahoo.com | D23: 0349 6639317 | E23: PESHAWAR | F23: Wrist Watch | G23: Accessories | H23: 46241 | I23: 1 | J23: 2500 | K23: =I23*J23 -> 2500 | L23: bank transfer | M23: Inactive | N23: 46247
A24: ORD-1023 | B24: Kashif Aslam | C24: kashif.aslam@outlook.com | D24: 03968072684 | E24: Sialkot | F24: Mobile Phone | G24: electronics | H24: 46206 | I24: 2 | J24: 8500 | K24: =I24*J24 -> 17000 | L24: Cash | M24: active | N24: 46208
A25: ORD-1024 | B25: Mahnoor Rana | C25: mahnoor.rana@outlook.com | D25: 0377-2921542 | E25: Karachi | F25: Air Fryer | G25: HOME APPLIANCES | H25: 46216 | I25: 5 | J25: 120000 | K25: =I25*J25 -> 600000 | L25: Credit Card | M25: pending | N25: 46218
A26: ORD-1025 | B26: Umar Malik | C26: umar.malik@gmail.com | D26: 0364-6724909 | E26: Sialkot | F26: Jacket | G26: APPAREL | H26: 46215 | I26: 5 | J26: 120000 | K26: =I26*J26 -> 600000 | L26: credit card | M26: inactive | N26: 46222
A27: ORD-1026 | B27: Noor Qureshi | C27: noor.qureshi@hotmail.com | D27: 0335-8563202 | F27: T-Shirt | G27: Apparel | H27: 46221 | I27: 3 | J27: 65000 | K27: =I27*J27 -> 195000 | L27: Cash | M27: active | N27: 46227
A28: ORD-1027 | B28: Junaid Abbasi | C28: junaid.abbasi@yahoo.com | D28: 03022561176 | E28: rawalpindi | F28: Jacket | G28: apparel | H28: 46239 | I28: 3 | J28: 45000 | K28: =I28*J28 -> 135000 | L28: credit card | M28: active | N28: 46243
A29: ORD-1028 | B29: Zeeshan Farooq | C29: zeeshan.farooq@yahoo.com | D29: 0375 9801946 | E29: karachi | F29: Jacket | G29: Apparel | H29: 46206 | I29: 5 | J29: 12000 | K29: =I29*J29 -> 60000 | L29: CASH | M29: pending | N29: 46208
A30: ORD-1072 | B30: Zeeshan Sheikh | D30: 03509479950 | E30: RAWALPINDI | F30: Mobile Phone | G30: electronics | H30: 46234 | I30: 5 | J30: 1500 | K30: =I30*J30 -> 7500 | L30: cash | M30: ACTIVE | N30: 46238
A31: ORD-1029 | B31: Ali Rana | C31: ali.rana@outlook.com | D31: 0361-2914064 | E31: Karachi | F31: Air Fryer | G31: home appliances | H31: 46230 | I31: 5 | J31: 85000 | K31: =I31*J31 -> 425000 | L31: Credit Card | M31: Inactive | N31: 46236
A32: ORD-1030 | B32: Asad Chaudhry | C32: asad.chaudhry@outlook.com | D32: 0394-2664863 | E32: FAISALABAD | F32: Sofa Set | G32: Furniture | H32: 46248 | I32: 4 | J32: 12000 | K32: =I32*J32 -> 48000 | L32: Cash | M32: Pending | N32: 46254
A33: ORD-1031 | B33: Noor Ali | C33: noor.ali@hotmail.com | D33: 0325-8132648 | E33: islamabad | F33: Headphones | G33: Electronics | H33: 46240 | I33: 4 | J33: 2500 | K33: =I33*J33 -> 10000 | L33: JazzCash | M33: Pending | N33: 46244
A34: ORD-1032 | B34: Rabia Anwar | C34: RABIA.ANWAR@OUTLOOK.COM | D34: 0341-5200476 | E34: LAHORE | F34: Office Chair | G34: furniture | H34: 46241 | I34: 4 | J34: 2500 | K34: =I34*J34 -> 10000 | L34: JazzCash | M34: ACTIVE | N34: 46246
A35: ORD-1033 | B35: Usman Sheikh | C35: usman.sheikh@outlook.com | D35: 03701615675 | E35: faisalabad | F35: Handbag | G35: ACCESSORIES | H35: 46233 | I35: 1 | J35: 8500 | K35: =I35*J35 -> 8500 | L35: jazzcash | M35: pending | N35: 46238
A36: ORD-1034 | B36: Asad Ahmed | C36: asad.ahmed@yahoo.com | D36: 0315 1484348 | E36: RAWALPINDI | F36: Vacuum Cleaner | G36: Home Appliances | H36: 46211 | I36: 1 | J36: 120000 | K36: =I36*J36 -> 120000 | L36: CASH | M36: Pending | N36: 46216
A37: ORD-1035 | B37: Rabia Qureshi | C37: rabia.qureshi@outlook.com | D37: 0376 9526867 | E37: KARACHI | F37: Sunglasses | G37: accessories | H37: 46222 | I37: 3 | J37: 85000 | K37: =I37*J37 -> 255000 | L37: Cash | M37: Inactive | N37: 46229
A38: ORD-1036 | B38: Asad Siddiqui | C38: asad.siddiqui@hotmail.com | D38: 0341 4165061 | E38: Peshawar | F38: Sunglasses | G38: Accessories | H38: 46228 | I38: 2 | J38: 45000 | K38: =I38*J38 -> 90000 | L38: Cash | M38: inactive | N38: 46233
A39: ORD-1037 | B39: Usman Baig | C39: usman.baig@outlook.com | D39: 03192255409 | E39: faisalabad | F39: Handbag | G39: ACCESSORIES | H39: 46238 | I39: 3 | J39: 120000 | K39: =I39*J39 -> 360000 | L39: JazzCash | M39: Active | N39: 46243
A40: ORD-1038 | B40: Nida Chaudhry | C40: nida.chaudhry@gmail.com | D40: 0312-8443690 | E40: Lahore | F40: Mobile Phone | G40: electronics | H40: 46230 | I40: 2 | J40: 4000 | K40: =I40*J40 -> 8000 | L40: CASH | M40: pending | N40: 46236
A41: ORD-1039 | B41: Nida Abbasi | C41: nida.abbasi@yahoo.com | D41: 03851157662 | E41: Islamabad | F41: Jacket | G41: APPAREL | H41: 46233 | I41: 2 | J41: 25000 | K41: =I41*J41 -> 50000 | L41: JazzCash | M41: Inactive | N41: 46237
A42: ORD-1040 | B42: Naveed Chaudhry | C42: naveed.chaudhry@hotmail.com | D42: 0301 1822825 | E42: Faisalabad | F42: Jacket | G42: Apparel | H42: 46250 | I42: 2 | J42: 120000 | K42: =I42*J42 -> 240000 | L42: cash | N42: 46257
A43: ORD-1041 | B43: Asad Ahmed | C43: asad.ahmed@yahoo.com | D43: 0322-4368777 | E43: MULTAN | F43: Bookshelf | G43: Furniture | H43: 46222 | I43: 3 | J43: 2500 | K43: =I43*J43 -> 7500 | L43: JazzCash | M43: active | N43: 46229
A44: ORD-1042 | B44: Tariq Aslam | C44: tariq.aslam@hotmail.com | D44: 03158630043 | E44: FAISALABAD | F44: Jacket | G44: Apparel | H44: 46239 | I44: 5 | J44: 8500 | K44: =I44*J44 -> 42500 | L44: cash | M44: Inactive | N44: 46243
A45: ORD-1043 | B45: Hira Qureshi | C45: hira.qureshi@gmail.com | D45: 0312 4939290 | E45: sialkot | F45: Vacuum Cleaner | G45: home appliances | H45: 46245 | I45: 4 | J45: 85000 | K45: =I45*J45 -> 340000 | L45: bank transfer | N45: 46247
A46: ORD-1044 | B46: Komal Raza | C46: komal.raza@yahoo.com | D46: 0369-7017548 | E46: Rawalpindi | F46: Wrist Watch | G46: Accessories | H46: 46205 | I46: 3 | J46: 8500 | K46: =I46*J46 -> 25500 | L46: CASH | M46: active | N46: 46207
A47: ORD-1045 | B47: Rida Raza | C47: rida.raza@yahoo.com | D47: 0300-5651899 | E47: Faisalabad | F47: Laptop | H47: 46224 | I47: 2 | J47: 12000 | K47: =I47*J47 -> 24000 | L47: Cash | M47: Inactive | N47: 46226
A48: ORD-1046 | B48: Bilal Abbasi | C48: bilal.abbasi@hotmail.com | D48: 0378 1727544 | E48: faisalabad | F48: Laptop | G48: Electronics | H48: 46210 | I48: 4 | J48: 2500 | K48: =I48*J48 -> 10000 | L48: cash | M48: active | N48: 46215
A49: ORD-1089 | B49: Ali Raza | C49: ali.raza@gmail.com | D49: 03894431161 | E49: multan | F49: Vacuum Cleaner | G49: HOME APPLIANCES | H49: 46235 | I49: 1 | J49: 45000 | K49: =I49*J49 -> 45000 | L49: Bank Transfer | M49: ACTIVE | N49: 46240
A50: ORD-1047 | B50: Rabia Awan | C50: rabia.awan@hotmail.com | D50: 0364-8217547 | E50: karachi | F50: Sofa Set | G50: furniture | H50: 46210 | I50: 4 | J50: 18000 | K50: =I50*J50 -> 72000 | L50: credit card | M50: active | N50: 46214
A51: ORD-1048 | B51: Faisal Ali | C51: faisal.ali@gmail.com | D51: 0316 2006313 | E51: MULTAN | F51: Jacket | G51: APPAREL | H51: 46207 | I51: 5 | J51: 12000 | K51: =I51*J51 -> 60000 | L51: Bank Transfer | M51: inactive | N51: 46211
A52: ORD-1049 | B52: Faisal Iqbal | C52: faisal.iqbal@hotmail.com | D52: 03734794319 | F52: Bookshelf | G52: FURNITURE | H52: 46215 | I52: 5 | J52: 120000 | K52: =I52*J52 -> 600000 | L52: bank transfer | M52: Pending | N52: 46218
A53: ORD-1050 | B53: Sara Ali | C53: sara.ali@yahoo.com | D53: 0339 6442241 | E53: lahore | F53: Water Dispenser | G53: Home Appliances | H53: 46235 | I53: 4 | J53: 25000 | K53: =I53*J53 -> 100000 | L53: credit card | M53: inactive | N53: 46241
A54: ORD-1051 | B54: Sadia Malik | C54: sadia.malik@outlook.com | D54: 0376-1919088 | E54: Rawalpindi | F54: Running Shoes | G54: apparel | H54: 46212 | I54: 5 | J54: 8500 | K54: =I54*J54 -> 42500 | L54: jazzcash | M54: Pending | N54: 46217
A55: ORD-1052 | B55: Bilal Aslam | C55: bilal.aslam@gmail.com | D55: 0340 8202195 | E55: peshawar | F55: Laptop | G55: electronics | H55: 46248 | I55: 1 | J55: 25000 | K55: =I55*J55 -> 25000 | L55: cash | M55: inactive | N55: 46252
A56: ORD-1053 | B56: Zainab Aslam | C56: zainab.aslam@hotmail.com | D56: 0381 2913049 | E56: multan | F56: LED TV | G56: Electronics | H56: 46213 | I56: 1 | J56: 4000 | K56: =I56*J56 -> 4000 | L56: JazzCash | M56: inactive | N56: 46220
A57: ORD-1054 | B57: Asad Rana | C57: asad.rana@hotmail.com | D57: 03088867190 | E57: FAISALABAD | F57: Microwave Oven | G57: Home Appliances | H57: 46222 | I57: 1 | J57: 85000 | K57: =I57*J57 -> 85000 | L57: Cash | M57: Inactive | N57: 46224
A58: ORD-1055 | B58: Hamza Baig | C58: hamza.baig@yahoo.com | D58: 0307-8558523 | E58: MULTAN | F58: Office Chair | G58: Furniture | H58: 46237 | I58: 2 | J58: 18000 | K58: =I58*J58 -> 36000 | L58: Bank Transfer | M58: Inactive | N58: 46243
A59: ORD-1056 | B59: Maryam Awan | C59: maryam.awan@hotmail.com | D59: 0336 5227787 | E59: islamabad | F59: LED TV | G59: electronics | H59: 46212 | I59: 1 | J59: 12000 | K59: =I59*J59 -> 12000 | L59: jazzcash | M59: pending | N59: 46218
A60: ORD-1075 | B60: Mahnoor Qureshi | C60: mahnoor.qureshi@gmail.com | D60: 0399 4817541 | E60: Sialkot | F60: Water Dispenser | G60: home appliances | H60: 46248 | I60: 2 | J60: 1500 | K60: =I60*J60 -> 3000 | L60: JazzCash | M60: active | N60: 46250
A61: ORD-1057 | B61: Hassan Anwar | C61: HASSAN.ANWAR@OUTLOOK.COM | D61: 03276733317 | E61: Islamabad | F61: Smart Watch | G61: ELECTRONICS | H61: 46206 | I61: 3 | J61: 85000 | K61: =I61*J61 -> 255000 | L61: CASH | M61: active | N61: 46213
A62: ORD-1058 | B62: Warda Sheikh | C62: warda.sheikh@gmail.com | D62: 0356 5780297 | E62: RAWALPINDI | F62: Blender | G62: Home Appliances | H62: 46233 | I62: 4 | J62: 65000 | K62: =I62*J62 -> 260000 | L62: jazzcash | M62: active | N62: 46237
A63: ORD-1059 | B63: Umar Butt | C63: umar.butt@gmail.com | D63: 0313-9655523 | E63: islamabad | F63: Microwave Oven | G63: Home Appliances | H63: 46232 | I63: 1 | J63: 25000 | K63: =I63*J63 -> 25000 | L63: Cash | M63: ACTIVE | N63: 46236
A64: ORD-1060 | B64: Zainab Javed | C64: zainab.javed@hotmail.com | D64: 0318-3308538 | E64: SIALKOT | F64: Blender | G64: home appliances | H64: 46217 | I64: 5 | J64: 85000 | K64: =I64*J64 -> 425000 | L64: jazzcash | M64: pending | N64: 46220
... A66: ORD-1062 | B66: Salman Siddiqui | C66: salman.siddiqui@outlook.com | D66: 03951272499 | E66: Multan | F66: Smart Watch | G66: ELECTRONICS | H66: 46238 | I66: 2 | J66: 120000 | K66: =I66*J66 -> 240000 | L66: JazzCash | M66: Inactive | N66: 46242
A67: ORD-1063 | B67: Hassan Ali | C67: hassan.ali@outlook.com | D67: 03056294819 | F67: Study Table | G67: furniture | H67: 46225 | I67: 1 | J67: 18000 | K67: =I67*J67 -> 18000 | L67: bank transfer | M67: Pending | N67: 46229
A68: ORD-1064 | B68: Imran Farooq | C68: imran.farooq@outlook.com | D68: 0334 2385991 | E68: PESHAWAR | F68: Office Chair | G68: FURNITURE | H68: 46222 | I68: 4 | J68: 85000 | K68: =I68*J68 -> 340000 | L68: bank transfer | M68: Inactive | N68: 46226
A69: ORD-1065 | B69: Hamza Javed | C69: hamza.javed@outlook.com | D69: 03097815076 | E69: Islamabad | F69: Water Dispenser | G69: HOME APPLIANCES | H69: 46253 | I69: 3 | J69: 18000 | K69: =I69*J69 -> 54000 | L69: bank transfer | M69: Active | N69: 46260
A70: ORD-1066 | B70: Asad Javed | C70: asad.javed@gmail.com | D70: 0383-5675638 | E70: lahore | F70: Handbag | G70: ACCESSORIES | H70: 46217 | I70: 3 | J70: 45000 | K70: =I70*J70 -> 135000 | L70: Credit Card | M70: pending | N70: 46223
A71: ORD-1067 | B71: Amna Baig | C71: amna.baig@hotmail.com | D71: 0337-6032437 | E71: islamabad | F71: Smart Watch | G71: Electronics | H71: 46227 | I71: 5 | J71: 18000 | K71: =I71*J71 -> 90000 | L71: JazzCash | M71: inactive | N71: 46233
A72: ORD-1068 | B72: Zainab Ali | C72: zainab.ali@outlook.com | D72: 03093102634 | E72: sialkot | F72: Jacket | G72: Apparel | H72: 46215 | I72: 4 | J72: 65000 | K72: =I72*J72 -> 260000 | L72: Cash | M72: inactive | N72: 46218
A73: ORD-1069 | B73: Fahad Sheikh | C73: fahad.sheikh@yahoo.com | D73: 0310-5204459 | E73: Faisalabad | F73: Water Dispenser | G73: HOME APPLIANCES | H73: 46241 | I73: 2 | J73: 120000 | K73: =I73*J73 -> 240000 | L73: Cash | M73: inactive | N73: 46244
A74: ORD-1070 | B74: Naveed Ahmed | C74: naveed.ahmed@gmail.com | D74: 0333 4536777 | E74: Lahore | F74: Vacuum Cleaner | G74: home appliances | H74: 46247 | I74: 3 | J74: 45000 | K74: =I74*J74 -> 135000 | L74: cash | M74: active | N74: 46252
A75: ORD-1071 | B75: Faisal Baig | C75: faisal.baig@yahoo.com | D75: 0344-7689354 | E75: KARACHI | F75: Smart Watch | G75: electronics | H75: 46228 | I75: 4 | J75: 8500 | K75: =I75*J75 -> 34000 | L75: CASH | M75: inactive | N75: 46234
A76: ORD-1072 | B76: Zeeshan Sheikh | D76: 03509479950 | E76: RAWALPINDI | F76: Mobile Phone | G76: electronics | H76: 46234 | I76: 5 | J76: 1500 | K76: =I76*J76 -> 7500 | L76: cash | M76: ACTIVE | N76: 46238
A77: ORD-1073 | B77: Farah Javed | C77: farah.javed@gmail.com | D77: 0309 7481857 | E77: FAISALABAD | F77: Smart Watch | G77: Electronics | H77: 46225 | I77: 3 | J77: 4000 | K77: =I77*J77 -> 12000 | L77: Credit Card | M77: Inactive | N77: 46231
A78: ORD-1067 | B78: Amna Baig | C78: amna.baig@hotmail.com | D78: 0337-6032437 | E78: islamabad | F78: Smart Watch | G78: Electronics | H78: 46227 | I78: 5 | J78: 18000 | K78: =I78*J78 -> 90000 | L78: JazzCash | M78: inactive | N78: 46233
A79: ORD-1074 | B79: Hamza Ahmed | C79: hamza.ahmed@hotmail.com | D79: 03653345135 | E79: Multan | F79: Water Dispenser | G79: HOME APPLIANCES | H79: 46236 | I79: 4 | J79: 85000 | K79: =I79*J79 -> 340000 | L79: credit card | M79: Active | N79: 46242
A80: ORD-1075 | B80: Mahnoor Qureshi | C80: mahnoor.qureshi@gmail.com | D80: 0399 4817541 | E80: Sialkot | F80: Water Dispenser | G80: home appliances | H80: 46248 | I80: 2 | J80: 1500 | K80: =I80*J80 -> 3000 | L80: JazzCash | M80: active | N80: 46250
A81: ORD-1076 | B81: Iqra Qureshi | C81: iqra.qureshi@outlook.com | D81: 0317-9702060 | E81: SIALKOT | F81: Office Chair | G81: furniture | H81: 46253 | I81: 3 | J81: 85000 | K81: =I81*J81 -> 255000 | L81: JazzCash | M81: active | N81: 46260
A82: ORD-1077 | B82: Hira Iqbal | C82: hira.iqbal@hotmail.com | D82: 03626319061 | E82: faisalabad | F82: Vacuum Cleaner | G82: home appliances | H82: 46253 | I82: 3 | J82: 1500 | K82: =I82*J82 -> 4500 | L82: credit card | M82: Active | N82: 46256
A83: ORD-1078 | B83: Asad Hussain | C83: asad.hussain@yahoo.com | D83: 0389-5557052 | E83: Rawalpindi | F83: Microwave Oven | G83: Home Appliances | H83: 46249 | I83: 1 | J83: 120000 | K83: =I83*J83 -> 120000 | M83: inactive | N83: 46254
A84: ORD-1079 | B84: Fahad Qureshi | C84: fahad.qureshi@outlook.com | D84: 0341 5788474 | E84: karachi | F84: Mobile Phone | G84: Electronics | H84: 46206 | I84: 4 | J84: 4000 | K84: =I84*J84 -> 16000 | L84: credit card | M84: Active | N84: 46211
A85: ORD-1080 | B85: Umar Malik | C85: umar.malik@hotmail.com | D85: 0363 3251501 | E85: Rawalpindi | F85: Wrist Watch | G85: ACCESSORIES | H85: 46254 | I85: 5 | J85: 120000 | K85: =I85*J85 -> 600000 | L85: Credit Card | M85: pending | N85: 46258
A86: ORD-1081 | B86: Farah Qureshi | C86: farah.qureshi@gmail.com | E86: Peshawar | F86: Bookshelf | G86: furniture | H86: 46245 | I86: 2 | J86: 1500 | K86: =I86*J86 -> 3000 | L86: cash | M86: active | N86: 46249
A87: ORD-1082 | B87: Salman Chaudhry | C87: salman.chaudhry@hotmail.com | D87: 03613570027 | E87: multan | F87: Blender | G87: HOME APPLIANCES | H87: 46247 | I87: 1 | J87: 65000 | K87: =I87*J87 -> 65000 | L87: JazzCash | M87: ACTIVE | N87: 46253
A88: ORD-1083 | B88: Naveed Malik | C88: naveed.malik@yahoo.com | D88: 0366-8412854 | E88: Sialkot | F88: Wrist Watch | G88: Accessories | H88: 46207 | I88: 4 | J88: 120000 | K88: =I88*J88 -> 480000 | L88: credit card | M88: Inactive | N88: 46213
A89: ORD-1084 | B89: Ali Raza | C89: ali.raza@gmail.com | E89: Peshawar | F89: Sunglasses | G89: accessories | H89: 46228 | I89: 1 | J89: 120000 | K89: =I89*J89 -> 120000 | L89: jazzcash | M89: pending | N89: 46233
A90: ORD-1085 | B90: Amna Siddiqui | D90: 03026005700 | E90: PESHAWAR | F90: Sofa Set | G90: Furniture | H90: 46250 | I90: 1 | J90: 120000 | K90: =I90*J90 -> 120000 | L90: bank transfer | M90: Active | N90: 46252
A91: ORD-1086 | B91: Bilal Malik | D91: 03941742169 | E91: Rawalpindi | F91: Running Shoes | G91: Apparel | H91: 46242 | I91: 3 | J91: 8500 | K91: =I91*J91 -> 25500 | L91: credit card | M91: Pending | N91: 46249
A92: ORD-1087 | B92: Junaid Chaudhry | C92: junaid.chaudhry@yahoo.com | D92: 0344 7394713 | E92: peshawar | F92: Handbag | G92: Accessories | H92: 46223 | I92: 2 | J92: 45000 | K92: =I92*J92 -> 90000 | L92: Cash | M92: Inactive | N92: 46230
A93: ORD-1088 | B93: Hassan Aslam | C93: HASSAN.ASLAM@YAHOO.COM | D93: 0347 2551288 | E93: Rawalpindi | F93: Water Dispenser | H93: 46241 | I93: 5 | J93: 8500 | K93: =I93*J93 -> 42500 | L93: JazzCash | M93: ACTIVE | N93: 46248
A94: ORD-1089 | B94: Ali Raza | C94: ali.raza@gmail.com | D94: 03894431161 | E94: multan | F94: Vacuum Cleaner | G94: HOME APPLIANCES | H94: 46235 | I94: 1 | J94: 45000 | K94: =I94*J94 -> 45000 | L94: Bank Transfer | M94: ACTIVE | N94: 46240
A95: ORD-1090 | B95: Hamza Rana | C95: hamza.rana@yahoo.com | D95: 03928005797 | E95: Multan | F95: Sofa Set | G95: furniture | H95: 46252 | I95: 4 | J95: 45000 | K95: =I95*J95 -> 180000 | L95: CASH | M95: ACTIVE | N95: 46257
A96: ORD-1091 | B96: Danish Abbasi | C96: danish.abbasi@gmail.com | D96: 0385-1813936 | E96: Rawalpindi | F96: Laptop | G96: Electronics | H96: 46246 | I96: 4 | J96: 120000 | K96: =I96*J96 -> 480000 | M96: inactive | N96: 46252
A97: ORD-1092 | B97: Ali Khan | C97: ali.khan@hotmail.com | D97: 0389-8223819 | E97: karachi | F97: Water Dispenser | G97: HOME APPLIANCES | H97: 46209 | I97: 4 | J97: 45000 | K97: =I97*J97 -> 180000 | L97: Cash | M97: Pending | N97: 46213
A98: ORD-1093 | B98: Zainab Ahmed | C98: zainab.ahmed@outlook.com | D98: 0389-3875339 | E98: PESHAWAR | F98: Air Fryer | G98: Home Appliances | H98: 46248 | I98: 4 | J98: 12000 | K98: =I98*J98 -> 48000 | L98: Cash | M98: Pending | N98: 46254
A99: ORD-1094 | B99: Danish Rana | C99: danish.rana@yahoo.com | D99: 0375 3419132 | E99: KARACHI | F99: Sofa Set | G99: FURNITURE | H99: 46225 | I99: 2 | J99: 2500 | K99: =I99*J99 -> 5000 | L99: jazzcash | M99: ACTIVE | N99: 46230
A100: ORD-1095 | B100: Sadia Iqbal | C100: sadia.iqbal@hotmail.com | D100: 0399-6475691 | E100: sialkot | F100: Vacuum Cleaner | G100: home appliances | H100: 46209 | I100: 3 | J100: 8500 | K100: =I100*J100 -> 25500 | L100: cash | M100: active | N100: 46215
A101: ORD-1096 | B101: Sana Aslam | C101: sana.aslam@gmail.com | D101: 0397-5525929 | E101: islamabad | F101: Vacuum Cleaner | G101: HOME APPLIANCES | H101: 46209 | I101: 5 | J101: 18000 | K101: =I101*J101 -> 90000 | M101: Inactive | N101: 46215
...

Sheet Pivot_Tables
A2: Row Labels | B2: Sum of Total_Sales | D2: Row Labels | E2: Sum of Total_Sales
A3: Home Appliances | B3: 4068500 | D3: Bank Transfer | E3: 1813000
A4: Accessories | B4: 3308000 | D4: Cash | E4: 3974000
A5: Electronics | B5: 2413000 | D5: Credit Card | E5: 4299500
A6: Furniture | B6: 2196500 | D6: JazzCash | E6: 2476500
A7: Apparel | B7: 1710500 | D7: Not Specified | E7: 1290000
A8: Unknown | B8: 156500 | D8: Grand Total | E8: 13853000
A9: Grand Total | B9: 13853000
A12: Row Labels | B12: Sum of Total_Sales | D12: Row Labels | E12: Sum of Total_Sales
A13: Faisalabad | B13: 3155500 | D13: 2026 | E13: 13853000
A14: Sialkot | B14: 2459000 | D14: Jul | E14: 7724500
A15: Rawalpindi | B15: 2043000 | D15: Aug | E15: 6128500
A16: Karachi | B16: 1695000 | D16: Grand Total | E16: 13853000
A17: Peshawar | B17: 1143500
A18: Islamabad | B18: 1061500
A19: Multan | B19: 1004500
A20: Unknown | B20: 813000
A21: Lahore | B21: 478000
A22: Grand Total | B22: 13853000

Sheet Dashboard
B3: Total Sales | D3: Total Orders | F3: Total Quantity | H3: Average Order Value
B4: =SUM(SalesData[Total_Sales]) -> 13853000 | D4: =COUNTA(SalesData[Order_ID]) -> 103 | F4: =SUM(SalesData[Quantity]) -> 323 | H4: =AVERAGE(SalesData[Total_Sales]) -> 134495.15

Sheet Sales_Dashboard

Sheet Cleaned_Data
A1: Order_ID | B1: Customer_Name | C1: Email | D1: Phone | E1: Phone_Cleaned | F1: City | G1: Product | H1: Category | I1: Order_Date | J1: Quantity | K1: Unit_Price | L1: Total_Sales | M1: Payment_Method | N1: Customer_Status | O1: Delivery_Date | P1: Order_Prefix (Left) | Q1: Order_Number (Right) | R1: Separator_Position | S1: MID_Number
A2: ORD-1012 | B2: =CLEAN(TRIM(Raw_Data!B13)) -> Noor Farooq | C2: noor.farooq@gmail.com | D2: 0312 2229110 | E2: =SUBSTITUTE(SUBSTITUTE(D2,"-","")," ","") -> 03122229110 | F2: =TRIM(PROPER(Raw_Data!E13)) -> Faisalabad | G2: =TRIM(PROPER(Raw_Data!F13)) -> Headphones | H2: =TRIM(PROPER(Raw_Data!G13)) -> Electronics | I2: 46249 | J2: 5 | K2: 120000 | L2: =J2*K2 -> 600000 | M2: Not Specified | N2: Pending | O2: 46253 | P2: =LEFT(A2,3) -> ORD | Q2: =RIGHT(A2,4) -> 1012 | R2: =FIND("-",A2) -> 4 | S2: =MID(A2,FIND("-",A2)+1,4) -> 1012
A3: ORD-1024 | B3: =CLEAN(TRIM(Raw_Data!B25)) -> Mahnoor Rana | C3: mahnoor.rana@outlook.com | D3: 0377-2921542 | E3: =SUBSTITUTE(SUBSTITUTE(D3,"-","")," ","") -> 03772921542 | F3: =TRIM(PROPER(Raw_Data!E25)) -> Karachi | G3: =TRIM(PROPER(Raw_Data!F25)) -> Air Fryer | H3: =TRIM(PROPER(Raw_Data!G25)) -> Home Appliances | I3: 46216 | J3: 5 | K3: 120000 | L3: =J3*K3 -> 600000 | M3: Credit Card | N3: Pending | O3: 46218 | P3: =LEFT(A3,3) -> ORD | Q3: =RIGHT(A3,4) -> 1024 | R3: =FIND("-",A3) -> 4 | S3: =MID(A3,FIND("-",A3)+1,4) -> 1024
A4: ORD-1025 | B4: =CLEAN(TRIM(Raw_Data!B26)) -> Umar Malik | C4: umar.malik@gmail.com | D4: 0364-6724909 | E4: =SUBSTITUTE(SUBSTITUTE(D4,"-","")," ","") -> 03646724909 | F4: =TRIM(PROPER(Raw_Data!E26)) -> Sialkot | G4: =TRIM(PROPER(Raw_Data!F26)) -> Jacket | H4: =TRIM(PROPER(Raw_Data!G26)) -> Apparel | I4: 46215 | J4: 5 | K4: 120000 | L4: =J4*K4 -> 600000 | M4: Credit Card | N4: InActive | O4: 46222 | P4: =LEFT(A4,3) -> ORD | Q4: =RIGHT(A4,4) -> 1025 | R4: =FIND("-",A4) -> 4 | S4: =MID(A4,FIND("-",A4)+1,4) -> 1025
A5: ORD-1049 | B5: =CLEAN(TRIM(Raw_Data!B52)) -> Faisal Iqbal | C5: faisal.iqbal@hotmail.com | D5: 03734794319 | E5: =SUBSTITUTE(SUBSTITUTE(D5,"-","")," ","") -> 03734794319 | F5: Unknown | G5: =TRIM(PROPER(Raw_Data!F52)) -> Bookshelf | H5: Furniture | I5: 46215 | J5: 5 | K5: 120000 | L5: =J5*K5 -> 600000 | M5: Bank Transfer | N5: Pending | O5: 46218 | P5: =LEFT(A5,3) -> ORD | Q5: =RIGHT(A5,4) -> 1049 | R5: =FIND("-",A5) -> 4 | S5: =MID(A5,FIND("-",A5)+1,4) -> 1049
A6: ORD-1080 | B6: =CLEAN(TRIM(Raw_Data!B85)) -> Umar Malik | C6: umar.malik@hotmail.com | D6: 0363 3251501 | E6: =SUBSTITUTE(SUBSTITUTE(D6,"-","")," ","") -> 03633251501 | F6: =TRIM(PROPER(Raw_Data!E85)) -> Rawalpindi | G6: =TRIM(PROPER(Raw_Data!F85)) -> Wrist Watch | H6: Accessories | I6: 46254 | J6: 5 | K6: 120000 | L6: =J6*K6 -> 600000 | M6: Credit Card | N6: Pending | O6: 46258 | P6: =LEFT(A6,3) -> ORD | Q6: =RIGHT(A6,4) -> 1080 | R6: =FIND("-",A6) -> 4 | S6: =MID(A6,FIND("-",A6)+1,4) -> 1080
A7: ORD-1017 | B7: =CLEAN(TRIM(Raw_Data!B18)) -> Anum Siddiqui | C7: anum.siddiqui@yahoo.com | D7: 0342 6266630 | E7: =SUBSTITUTE(SUBSTITUTE(D7,"-","")," ","") -> 03426266630 | F7: =TRIM(PROPER(Raw_Data!E18)) -> Faisalabad | G7: =TRIM(PROPER(Raw_Data!F18)) -> Sunglasses | H7: =TRIM(PROPER(Raw_Data!G18)) -> Accessories | I7: 46230 | J7: 4 | K7: 120000 | L7: =J7*K7 -> 480000 | M7: Cash | N7: Active | O7: 46237 | P7: =LEFT(A7,3) -> ORD | Q7: =RIGHT(A7,4) -> 1017 | R7: =FIND("-",A7) -> 4 | S7: =MID(A7,FIND("-",A7)+1,4) -> 1017
A8: ORD-1083 | B8: =CLEAN(TRIM(Raw_Data!B88)) -> Naveed Malik | C8: naveed.malik@yahoo.com | D8: 0366-8412854 | E8: =SUBSTITUTE(SUBSTITUTE(D8,"-","")," ","") -> 03668412854 | F8: =TRIM(PROPER(Raw_Data!E88)) -> Sialkot | G8: =TRIM(PROPER(Raw_Data!F88)) -> Wrist Watch | H8: Accessories | I8: 46207 | J8: 4 | K8: 120000 | L8: =J8*K8 -> 480000 | M8: Credit Card | N8: InActive | O8: 46213 | P8: =LEFT(A8,3) -> ORD | Q8: =RIGHT(A8,4) -> 1083 | R8: =FIND("-",A8) -> 4 | S8: =MID(A8,FIND("-",A8)+1,4) -> 1083
A9: ORD-1091 | B9: =CLEAN(TRIM(Raw_Data!B96)) -> Danish Abbasi | C9: danish.abbasi@gmail.com | D9: 0385-1813936 | E9: =SUBSTITUTE(SUBSTITUTE(D9,"-","")," ","") -> 03851813936 | F9: =TRIM(PROPER(Raw_Data!E96)) -> Rawalpindi | G9: =TRIM(PROPER(Raw_Data!F96)) -> Laptop | H9: Electronics | I9: 46246 | J9: 4 | K9: 120000 | L9: =J9*K9 -> 480000 | M9: Not Specified | N9: InActive | O9: 46252 | P9: =LEFT(A9,3) -> ORD | Q9: =RIGHT(A9,4) -> 1091 | R9: =FIND("-",A9) -> 4 | S9: =MID(A9,FIND("-",A9)+1,4) -> 1091
A10: ORD-1029 | B10: =CLEAN(TRIM(Raw_Data!B31)) -> Ali Rana | C10: ali.rana@outlook.com | D10: 0361-2914064 | E10: =SUBSTITUTE(SUBSTITUTE(D10,"-","")," ","") -> 03612914064 | F10: =TRIM(PROPER(Raw_Data!E31)) -> Karachi | G10: =TRIM(PROPER(Raw_Data!F31)) -> Air Fryer | H10: =TRIM(PROPER(Raw_Data!G31)) -> Home Appliances | I10: 46230 | J10: 5 | K10: 85000 | L10: =J10*K10 -> 425000 | M10: Credit Card | N10: InActive | O10: 46236 | P10: =LEFT(A10,3) -> ORD | Q10: =RIGHT(A10,4) -> 1029 | R10: =FIND("-",A10) -> 4 | S10: =MID(A10,FIND("-",A10)+1,4) -> 1029
A11: ORD-1060 | B11: =CLEAN(TRIM(Raw_Data!B64)) -> Zainab Javed | C11: zainab.javed@hotmail.com | D11: 0318-3308538 | E11: =SUBSTITUTE(SUBSTITUTE(D11,"-","")," ","") -> 03183308538 | F11: =TRIM(PROPER(Raw_Data!E64)) -> Sialkot | G11: =TRIM(PROPER(Raw_Data!F64)) -> Blender | H11: Home Appliances | I11: 46217 | J11: 5 | K11: 85000 | L11: =J11*K11 -> 425000 | M11: JazzCash | N11: Pending | O11: 46220 | P11: =LEFT(A11,3) -> ORD | Q11: =RIGHT(A11,4) -> 1060 | R11: =FIND("-",A11) -> 4 | S11: =MID(A11,FIND("-",A11)+1,4) -> 1060
A12: ORD-1003 | B12: =CLEAN(TRIM(Raw_Data!B4)) -> Waqas Ali | C12: waqas.ali@gmail.com | D12: 03207210606 | E12: =SUBSTITUTE(SUBSTITUTE(D12,"-","")," ","") -> 03207210606 | F12: =TRIM(PROPER(Raw_Data!E4)) -> Faisalabad | G12: =TRIM(PROPER(Raw_Data!F4)) -> Headphones | H12: =TRIM(PROPER(Raw_Data!G4)) -> Electronics | I12: 46233 | J12: 3 | K12: 120000 | L12: =J12*K12 -> 360000 | M12: JazzCash | N12: Active | O12: 46238 | P12: =LEFT(A12,3) -> ORD | Q12: =RIGHT(A12,4) -> 1003 | R12: =FIND("-",A12) -> 4 | S12: =MID(A12,FIND("-",A12)+1,4) -> 1003
A13: ORD-1037 | B13: =CLEAN(TRIM(Raw_Data!B39)) -> Usman Baig | C13: usman.baig@outlook.com | D13: 03192255409 | E13: =SUBSTITUTE(SUBSTITUTE(D13,"-","")," ","") -> 03192255409 | F13: =TRIM(PROPER(Raw_Data!E39)) -> Faisalabad | G13: =TRIM(PROPER(Raw_Data!F39)) -> Handbag | H13: =TRIM(PROPER(Raw_Data!G39)) -> Accessories | I13: 46238 | J13: 3 | K13: 120000 | L13: =J13*K13 -> 360000 | M13: JazzCash | N13: Active | O13: 46243 | P13: =LEFT(A13,3) -> ORD | Q13: =RIGHT(A13,4) -> 1037 | R13: =FIND("-",A13) -> 4 | S13: =MID(A13,FIND("-",A13)+1,4) -> 1037
A14: ORD-1016 | B14: =CLEAN(TRIM(Raw_Data!B17)) -> Rabia Javed | C14: rabia.javed@outlook.com | D14: 03032935113 | E14: =SUBSTITUTE(SUBSTITUTE(D14,"-","")," ","") -> 03032935113 | F14: =TRIM(PROPER(Raw_Data!E17)) -> Faisalabad | G14: =TRIM(PROPER(Raw_Data!F17)) -> Sunglasses | H14: =TRIM(PROPER(Raw_Data!G17)) -> Accessories | I14: 46236 | J14: 4 | K14: 85000 | L14: =J14*K14 -> 340000 | M14: Credit Card | N14: Pending | O14: 46238 | P14: =LEFT(A14,3) -> ORD | Q14: =RIGHT(A14,4) -> 1016 | R14: =FIND("-",A14) -> 4 | S14: =MID(A14,FIND("-",A14)+1,4) -> 1016
A15: ORD-1043 | B15: =CLEAN(TRIM(Raw_Data!B45)) -> Hira Qureshi | C15: hira.qureshi@gmail.com | D15: 0312 4939290 | E15: =SUBSTITUTE(SUBSTITUTE(D15,"-","")," ","") -> 03124939290 | F15: =TRIM(PROPER(Raw_Data!E45)) -> Sialkot | G15: =TRIM(PROPER(Raw_Data!F45)) -> Vacuum Cleaner | H15: =TRIM(PROPER(Raw_Data!G45)) -> Home Appliances | I15: 46245 | J15: 4 | K15: 85000 | L15: =J15*K15 -> 340000 | M15: Bank Transfer | N15: Unknown | O15: 46247 | P15: =LEFT(A15,3) -> ORD | Q15: =RIGHT(A15,4) -> 1043 | R15: =FIND("-",A15) -> 4 | S15: =MID(A15,FIND("-",A15)+1,4) -> 1043
A16: ORD-1064 | B16: =CLEAN(TRIM(Raw_Data!B68)) -> Imran Farooq | C16: imran.farooq@outlook.com | D16: 0334 2385991 | E16: =SUBSTITUTE(SUBSTITUTE(D16,"-","")," ","") -> 03342385991 | F16: =TRIM(PROPER(Raw_Data!E68)) -> Peshawar | G16: =TRIM(PROPER(Raw_Data!F68)) -> Office Chair | H16: Furniture | I16: 46222 | J16: 4 | K16: 85000 | L16: =J16*K16 -> 340000 | M16: Bank Transfer | N16: InActive | O16: 46226 | P16: =LEFT(A16,3) -> ORD | Q16: =RIGHT(A16,4) -> 1064 | R16: =FIND("-",A16) -> 4 | S16: =MID(A16,FIND("-",A16)+1,4) -> 1064
A17: ORD-1074 | B17: =CLEAN(TRIM(Raw_Data!B79)) -> Hamza Ahmed | C17: hamza.ahmed@hotmail.com | D17: 03653345135 | E17: =SUBSTITUTE(SUBSTITUTE(D17,"-","")," ","") -> 03653345135 | F17: =TRIM(PROPER(Raw_Data!E79)) -> Multan | G17: =TRIM(PROPER(Raw_Data!F79)) -> Water Dispenser | H17: Home Appliances | I17: 46236 | J17: 4 | K17: 85000 | L17: =J17*K17 -> 340000 | M17: Credit Card | N17: Active | O17: 46242 | P17: =LEFT(A17,3) -> ORD | Q17: =RIGHT(A17,4) -> 1074 | R17: =FIND("-",A17) -> 4 | S17: =MID(A17,FIND("-",A17)+1,4) -> 1074
A18: ORD-1097 | B18: =CLEAN(TRIM(Raw_Data!B102)) -> Zainab Siddiqui | C18: zainab.siddiqui@yahoo.com | D18: 03175511711 | E18: =SUBSTITUTE(SUBSTITUTE(D18,"-","")," ","") -> 03175511711 | F18: =TRIM(PROPER(Raw_Data!E102)) -> Islamabad | G18: =TRIM(PROPER(Raw_Data!F102)) -> Bookshelf | H18: Furniture | I18: 46219 | J18: 4 | K18: 85000 | L18: =J18*K18 -> 340000 | M18: Cash | N18: Active | O18: 46226 | P18: =LEFT(A18,3) -> ORD | Q18: =RIGHT(A18,4) -> 1097 | R18: =FIND("-",A18) -> 4 | S18: =MID(A18,FIND("-",A18)+1,4) -> 1097
A19: ORD-1058 | B19: =CLEAN(TRIM(Raw_Data!B62)) -> Warda Sheikh | C19: warda.sheikh@gmail.com | D19: 0356 5780297 | E19: =SUBSTITUTE(SUBSTITUTE(D19,"-","")," ","") -> 03565780297 | F19: =TRIM(PROPER(Raw_Data!E62)) -> Rawalpindi | G19: =TRIM(PROPER(Raw_Data!F62)) -> Blender | H19: Home Appliances | I19: 46233 | J19: 4 | K19: 65000 | L19: =J19*K19 -> 260000 | M19: JazzCash | N19: Active | O19: 46237 | P19: =LEFT(A19,3) -> ORD | Q19: =RIGHT(A19,4) -> 1058 | R19: =FIND("-",A19) -> 4 | S19: =MID(A19,FIND("-",A19)+1,4) -> 1058
A20: ORD-1068 | B20: =CLEAN(TRIM(Raw_Data!B72)) -> Zainab Ali | C20: zainab.ali@outlook.com | D20: 03093102634 | E20: =SUBSTITUTE(SUBSTITUTE(D20,"-","")," ","") -> 03093102634 | F20: =TRIM(PROPER(Raw_Data!E72)) -> Sialkot | G20: =TRIM(PROPER(Raw_Data!F72)) -> Jacket | H20: Apparel | I20: 46215 | J20: 4 | K20: 65000 | L20: =J20*K20 -> 260000 | M20: Cash | N20: InActive | O20: 46218 | P20: =LEFT(A20,3) -> ORD | Q20: =RIGHT(A20,4) -> 1068 | R20: =FIND("-",A20) -> 4 | S20: =MID(A20,FIND("-",A20)+1,4) -> 1068
A21: ORD-1002 | B21: =CLEAN(TRIM(Raw_Data!B3)) -> Fahad Qureshi | C21: fahad.qureshi@yahoo.com | D21: 03482622631 | E21: =SUBSTITUTE(SUBSTITUTE(D21,"-","")," ","") -> 03482622631 | F21: =TRIM(PROPER(Raw_Data!E3)) -> Faisalabad | G21: =TRIM(PROPER(Raw_Data!F3)) -> Vacuum Cleaner | H21: =TRIM(PROPER(Raw_Data!G3)) -> Home Appliances | I21: 46244 | J21: 3 | K21: 85000 | L21: =J21*K21 -> 255000 | M21: Credit Card | N21: Active | O21: 46250 | P21: =LEFT(A21,3) -> ORD | Q21: =RIGHT(A21,4) -> 1002 | R21: =FIND("-",A21) -> 4 | S21: =MID(A21,FIND("-",A21)+1,4) -> 1002
A22: ORD-1035 | B22: =CLEAN(TRIM(Raw_Data!B37)) -> Rabia Qureshi | C22: rabia.qureshi@outlook.com | D22: 0376 9526867 | E22: =SUBSTITUTE(SUBSTITUTE(D22,"-","")," ","") -> 03769526867 | F22: =TRIM(PROPER(Raw_Data!E37)) -> Karachi | G22: =TRIM(PROPER(Raw_Data!F37)) -> Sunglasses | H22: =TRIM(PROPER(Raw_Data!G37)) -> Accessories | I22: 46222 | J22: 3 | K22: 85000 | L22: =J22*K22 -> 255000 | M22: Cash | N22: InActive | O22: 46229 | P22: =LEFT(A22,3) -> ORD | Q22: =RIGHT(A22,4) -> 1035 | R22: =FIND("-",A22) -> 4 | S22: =MID(A22,FIND("-",A22)+1,4) -> 1035
A23: ORD-1057 | B23: =CLEAN(TRIM(Raw_Data!B61)) -> Hassan Anwar | C23: hassan.anwar@outlook.com | D23: 03276733317 | E23: =SUBSTITUTE(SUBSTITUTE(D23,"-","")," ","") -> 03276733317 | F23: =TRIM(PROPER(Raw_Data!E61)) -> Islamabad | G23: =TRIM(PROPER(Raw_Data!F61)) -> Smart Watch | H23: Electronics | I23: 46206 | J23: 3 | K23: 85000 | L23: =J23*K23 -> 255000 | M23: Cash | N23: Active | O23: 46213 | P23: =LEFT(A23,3) -> ORD | Q23: =RIGHT(A23,4) -> 1057 | R23: =FIND("-",A23) -> 4 | S23: =MID(A23,FIND("-",A23)+1,4) -> 1057
A24: ORD-1076 | B24: =CLEAN(TRIM(Raw_Data!B81)) -> Iqra Qureshi | C24: iqra.qureshi@outlook.com | D24: 0317-9702060 | E24: =SUBSTITUTE(SUBSTITUTE(D24,"-","")," ","") -> 03179702060 | F24: =TRIM(PROPER(Raw_Data!E81)) -> Sialkot | G24: =TRIM(PROPER(Raw_Data!F81)) -> Office Chair | H24: Furniture | I24: 46253 | J24: 3 | K24: 85000 | L24: =J24*K24 -> 255000 | M24: JazzCash | N24: Active | O24: 46260 | P24: =LEFT(A24,3) -> ORD | Q24: =RIGHT(A24,4) -> 1076 | R24: =FIND("-",A24) -> 4 | S24: =MID(A24,FIND("-",A24)+1,4) -> 1076
A25: ORD-1040 | B25: =CLEAN(TRIM(Raw_Data!B42)) -> Naveed Chaudhry | C25: naveed.chaudhry@hotmail.com | D25: 0301 1822825 | E25: =SUBSTITUTE(SUBSTITUTE(D25,"-","")," ","") -> 03011822825 | F25: =TRIM(PROPER(Raw_Data!E42)) -> Faisalabad | G25: =TRIM(PROPER(Raw_Data!F42)) -> Jacket | H25: =TRIM(PROPER(Raw_Data!G42)) -> Apparel | I25: 46250 | J25: 2 | K25: 120000 | L25: =J25*K25 -> 240000 | M25: Cash | N25: Unknown | O25: 46257 | P25: =LEFT(A25,3) -> ORD | Q25: =RIGHT(A25,4) -> 1040 | R25: =FIND("-",A25) -> 4 | S25: =MID(A25,FIND("-",A25)+1,4) -> 1040
A26: ORD-1062 | B26: =CLEAN(TRIM(Raw_Data!B66)) -> Salman Siddiqui | C26: salman.siddiqui@outlook.com | D26: 03951272499 | E26: =SUBSTITUTE(SUBSTITUTE(D26,"-","")," ","") -> 03951272499 | F26: =TRIM(PROPER(Raw_Data!E66)) -> Multan | G26: =TRIM(PROPER(Raw_Data!F66)) -> Smart Watch | H26: Electronics | I26: 46238 | J26: 2 | K26: 120000 | L26: =J26*K26 -> 240000 | M26: JazzCash | N26: InActive | O26: 46242 | P26: =LEFT(A26,3) -> ORD | Q26: =RIGHT(A26,4) -> 1062 | R26: =FIND("-",A26) -> 4 | S26: =MID(A26,FIND("-",A26)+1,4) -> 1062
A27: ORD-1069 | B27: =CLEAN(TRIM(Raw_Data!B73)) -> Fahad Sheikh | C27: fahad.sheikh@yahoo.com | D27: 0310-5204459 | E27: =SUBSTITUTE(SUBSTITUTE(D27,"-","")," ","") -> 03105204459 | F27: =TRIM(PROPER(Raw_Data!E73)) -> Faisalabad | G27: =TRIM(PROPER(Raw_Data!F73)) -> Water Dispenser | H27: Home Appliances | I27: 46241 | J27: 2 | K27: 120000 | L27: =J27*K27 -> 240000 | M27: Cash | N27: InActive | O27: 46244 | P27: =LEFT(A27,3) -> ORD | Q27: =RIGHT(A27,4) -> 1069 | R27: =FIND("-",A27) -> 4 | S27: =MID(A27,FIND("-",A27)+1,4) -> 1069
A28: ORD-1026 | B28: =CLEAN(TRIM(Raw_Data!B27)) -> Noor Qureshi | C28: noor.qureshi@hotmail.com | D28: 0335-8563202 | E28: =SUBSTITUTE(SUBSTITUTE(D28,"-","")," ","") -> 03358563202 | F28: Unknown | G28: =TRIM(PROPER(Raw_Data!F27)) -> T-Shirt | H28: =TRIM(PROPER(Raw_Data!G27)) -> Apparel | I28: 46221 | J28: 3 | K28: 65000 | L28: =J28*K28 -> 195000 | M28: Cash | N28: Active | O28: 46227 | P28: =LEFT(A28,3) -> ORD | Q28: =RIGHT(A28,4) -> 1026 | R28: =FIND("-",A28) -> 4 | S28: =MID(A28,FIND("-",A28)+1,4) -> 1026
A29: ORD-1021 | B29: =CLEAN(TRIM(Raw_Data!B22)) -> Danish Ali | C29: danish.ali@yahoo.com | D29: 03537838382 | E29: =SUBSTITUTE(SUBSTITUTE(D29,"-","")," ","") -> 03537838382 | F29: =TRIM(PROPER(Raw_Data!E22)) -> Peshawar | G29: =TRIM(PROPER(Raw_Data!F22)) -> Sunglasses | H29: =TRIM(PROPER(Raw_Data!G22)) -> Accessories | I29: 46252 | J29: 4 | K29: 45000 | L29: =J29*K29 -> 180000 | M29: Cash | N29: Active | O29: 46258 | P29: =LEFT(A29,3) -> ORD | Q29: =RIGHT(A29,4) -> 1021 | R29: =FIND("-",A29) -> 4 | S29: =MID(A29,FIND("-",A29)+1,4) -> 1021
A30: ORD-1090 | B30: =CLEAN(TRIM(Raw_Data!B95)) -> Hamza Rana | C30: hamza.rana@yahoo.com | D30: 03928005797 | E30: =SUBSTITUTE(SUBSTITUTE(D30,"-","")," ","") -> 03928005797 | F30: =TRIM(PROPER(Raw_Data!E95)) -> Multan | G30: =TRIM(PROPER(Raw_Data!F95)) -> Sofa Set | H30: Furniture | I30: 46252 | J30: 4 | K30: 45000 | L30: =J30*K30 -> 180000 | M30: Cash | N30: Active | O30: 46257 | P30: =LEFT(A30,3) -> ORD | Q30: =RIGHT(A30,4) -> 1090 | R30: =FIND("-",A30) -> 4 | S30: =MID(A30,FIND("-",A30)+1,4) -> 1090
A31: ORD-1092 | B31: =CLEAN(TRIM(Raw_Data!B97)) -> Ali Khan | C31: ali.khan@hotmail.com | D31: 0389-8223819 | E31: =SUBSTITUTE(SUBSTITUTE(D31,"-","")," ","") -> 03898223819 | F31: =TRIM(PROPER(Raw_Data!E97)) -> Karachi | G31: =TRIM(PROPER(Raw_Data!F97)) -> Water Dispenser | H31: Home Appliances | I31: 46209 | J31: 4 | K31: 45000 | L31: =J31*K31 -> 180000 | M31: Cash | N31: Pending | O31: 46213 | P31: =LEFT(A31,3) -> ORD | Q31: =RIGHT(A31,4) -> 1092 | R31: =FIND("-",A31) -> 4 | S31: =MID(A31,FIND("-",A31)+1,4) -> 1092
A32: ORD-1027 | B32: =CLEAN(TRIM(Raw_Data!B28)) -> Junaid Abbasi | C32: junaid.abbasi@yahoo.com | D32: 03022561176 | E32: =SUBSTITUTE(SUBSTITUTE(D32,"-","")," ","") -> 03022561176 | F32: =TRIM(PROPER(Raw_Data!E28)) -> Rawalpindi | G32: =TRIM(PROPER(Raw_Data!F28)) -> Jacket | H32: =TRIM(PROPER(Raw_Data!G28)) -> Apparel | I32: 46239 | J32: 3 | K32: 45000 | L32: =J32*K32 -> 135000 | M32: Credit Card | N32: Active | O32: 46243 | P32: =LEFT(A32,3) -> ORD | Q32: =RIGHT(A32,4) -> 1027 | R32: =FIND("-",A32) -> 4 | S32: =MID(A32,FIND("-",A32)+1,4) -> 1027
A33: ORD-1066 | B33: =CLEAN(TRIM(Raw_Data!B70)) -> Asad Javed | C33: asad.javed@gmail.com | D33: 0383-5675638 | E33: =SUBSTITUTE(SUBSTITUTE(D33,"-","")," ","") -> 03835675638 | F33: =TRIM(PROPER(Raw_Data!E70)) -> Lahore | G33: =TRIM(PROPER(Raw_Data!F70)) -> Handbag | H33: Accessories | I33: 46217 | J33: 3 | K33: 45000 | L33: =J33*K33 -> 135000 | M33: Credit Card | N33: Pending | O33: 46223 | P33: =LEFT(A33,3) -> ORD | Q33: =RIGHT(A33,4) -> 1066 | R33: =FIND("-",A33) -> 4 | S33: =MID(A33,FIND("-",A33)+1,4) -> 1066
A34: ORD-1070 | B34: =CLEAN(TRIM(Raw_Data!B74)) -> Naveed Ahmed | C34: naveed.ahmed@gmail.com | D34: 0333 4536777 | E34: =SUBSTITUTE(SUBSTITUTE(D34,"-","")," ","") -> 03334536777 | F34: =TRIM(PROPER(Raw_Data!E74)) -> Lahore | G34: =TRIM(PROPER(Raw_Data!F74)) -> Vacuum Cleaner | H34: Home Appliances | I34: 46247 | J34: 3 | K34: 45000 | L34: =J34*K34 -> 135000 | M34: Cash | N34: Active | O34: 46252 | P34: =LEFT(A34,3) -> ORD | Q34: =RIGHT(A34,4) -> 1070 | R34: =FIND("-",A34) -> 4 | S34: =MID(A34,FIND("-",A34)+1,4) -> 1070
A35: ORD-1004 | B35: =CLEAN(TRIM(Raw_Data!B5)) -> Ayesha Iqbal | C35: ayesha.iqbal@hotmail.com | D35: 0372-6279418 | E35: =SUBSTITUTE(SUBSTITUTE(D35,"-","")," ","") -> 03726279418 | F35: =TRIM(PROPER(Raw_Data!E5)) -> Peshawar | G35: =TRIM(PROPER(Raw_Data!F5)) -> Bookshelf | H35: =TRIM(PROPER(Raw_Data!G5)) -> Furniture | I35: 46241 | J35: 5 | K35: 25000 | L35: =J35*K35 -> 125000 | M35: Bank Transfer | N35: Active | O35: 46246 | P35: =LEFT(A35,3) -> ORD | Q35: =RIGHT(A35,4) -> 1004 | R35: =FIND("-",A35) -> 4 | S35: =MID(A35,FIND("-",A35)+1,4) -> 1004
A36: ORD-1034 | B36: =CLEAN(TRIM(Raw_Data!B36)) -> Asad Ahmed | C36: asad.ahmed@yahoo.com | D36: 0315 1484348 | E36: =SUBSTITUTE(SUBSTITUTE(D36,"-","")," ","") -> 03151484348 | F36: =TRIM(PROPER(Raw_Data!E36)) -> Rawalpindi | G36: =TRIM(PROPER(Raw_Data!F36)) -> Vacuum Cleaner | H36: =TRIM(PROPER(Raw_Data!G36)) -> Home Appliances | I36: 46211 | J36: 1 | K36: 120000 | L36: =J36*K36 -> 120000 | M36: Cash | N36: Pending | O36: 46216 | P36: =LEFT(A36,3) -> ORD | Q36: =RIGHT(A36,4) -> 1034 | R36: =FIND("-",A36) -> 4 | S36: =MID(A36,FIND("-",A36)+1,4) -> 1034
A37: ORD-1078 | B37: =CLEAN(TRIM(Raw_Data!B83)) -> Asad Hussain | C37: asad.hussain@yahoo.com | D37: 0389-5557052 | E37: =SUBSTITUTE(SUBSTITUTE(D37,"-","")," ","") -> 03895557052 | F37: =TRIM(PROPER(Raw_Data!E83)) -> Rawalpindi | G37: =TRIM(PROPER(Raw_Data!F83)) -> Microwave Oven | H37: Home Appliances | I37: 46249 | J37: 1 | K37: 120000 | L37: =J37*K37 -> 120000 | M37: Not Specified | N37: InActive | O37: 46254 | P37: =LEFT(A37,3) -> ORD | Q37: =RIGHT(A37,4) -> 1078 | R37: =FIND("-",A37) -> 4 | S37: =MID(A37,FIND("-",A37)+1,4) -> 1078
A38: ORD-1084 | B38: =CLEAN(TRIM(Raw_Data!B89)) -> Ali Raza | C38: ali.raza@gmail.com | D38: Not Provided | E38: =SUBSTITUTE(SUBSTITUTE(D38,"-","")," ","") -> NotProvided | F38: =TRIM(PROPER(Raw_Data!E89)) -> Peshawar | G38: =TRIM(PROPER(Raw_Data!F89)) -> Sunglasses | H38: Accessories | I38: 46228 | J38: 1 | K38: 120000 | L38: =J38*K38 -> 120000 | M38: JazzCash | N38: Pending | O38: 46233 | P38: =LEFT(A38,3) -> ORD | Q38: =RIGHT(A38,4) -> 1084 | R38: =FIND("-",A38) -> 4 | S38: =MID(A38,FIND("-",A38)+1,4) -> 1084
A39: ORD-1085 | B39: =CLEAN(TRIM(Raw_Data!B90)) -> Amna Siddiqui | C39: Not Provided | D39: 3026005700 | E39: =SUBSTITUTE(SUBSTITUTE(D39,"-","")," ","") -> 3026005700 | F39: =TRIM(PROPER(Raw_Data!E90)) -> Peshawar | G39: =TRIM(PROPER(Raw_Data!F90)) -> Sofa Set | H39: Furniture | I39: 46250 | J39: 1 | K39: 120000 | L39: =J39*K39 -> 120000 | M39: Bank Transfer | N39: Active | O39: 46252 | P39: =LEFT(A39,3) -> ORD | Q39: =RIGHT(A39,4) -> 1085 | R39: =FIND("-",A39) -> 4 | S39: =MID(A39,FIND("-",A39)+1,4) -> 1085
A40: ORD-1050 | B40: =CLEAN(TRIM(Raw_Data!B53)) -> Sara Ali | C40: sara.ali@yahoo.com | D40: 0339 6442241 | E40: =SUBSTITUTE(SUBSTITUTE(D40,"-","")," ","") -> 03396442241 | F40: =TRIM(PROPER(Raw_Data!E53)) -> Lahore | G40: =TRIM(PROPER(Raw_Data!F53)) -> Water Dispenser | H40: Home Appliances | I40: 46235 | J40: 4 | K40: 25000 | L40: =J40*K40 -> 100000 | M40: Credit Card | N40: InActive | O40: 46241 | P40: =LEFT(A40,3) -> ORD | Q40: =RIGHT(A40,4) -> 1050 | R40: =FIND("-",A40) -> 4 | S40: =MID(A40,FIND("-",A40)+1,4) -> 1050
A41: ORD-1001 | B41: =CLEAN(TRIM(Raw_Data!B2)) -> Mahnoor Khan | C41: mahnoor.khan@yahoo.com | D41: 0369 2458591 | E41: =SUBSTITUTE(SUBSTITUTE(D41,"-","")," ","") -> 03692458591 | F41: =TRIM(PROPER(Raw_Data!E2)) -> Lahore | G41: =TRIM(PROPER(Raw_Data!F2)) -> Microwave Oven | H41: Unknown | I41: 46238 | J41: 2 | K41: 45000 | L41: =J41*K41 -> 90000 | M41: Cash | N41: Unknown | O41: 46243 | P41: =LEFT(A41,3) -> ORD | Q41: =RIGHT(A41,4) -> 1001 | R41: =FIND("-",A41) -> 4 | S41: =MID(A41,FIND("-",A41)+1,4) -> 1001
A42: ORD-1036 | B42: =CLEAN(TRIM(Raw_Data!B38)) -> Asad Siddiqui | C42: asad.siddiqui@hotmail.com | D42: 0341 4165061 | E42: =SUBSTITUTE(SUBSTITUTE(D42,"-","")," ","") -> 03414165061 | F42: =TRIM(PROPER(Raw_Data!E38)) -> Peshawar | G42: =TRIM(PROPER(Raw_Data!F38)) -> Sunglasses | H42: =TRIM(PROPER(Raw_Data!G38)) -> Accessories | I42: 46228 | J42: 2 | K42: 45000 | L42: =J42*K42 -> 90000 | M42: Cash | N42: InActive | O42: 46233 | P42: =LEFT(A42,3) -> ORD | Q42: =RIGHT(A42,4) -> 1036 | R42: =FIND("-",A42) -> 4 | S42: =MID(A42,FIND("-",A42)+1,4) -> 1036
A43: ORD-1067 | B43: =CLEAN(TRIM(Raw_Data!B71)) -> Amna Baig | C43: amna.baig@hotmail.com | D43: 0337-6032437 | E43: =SUBSTITUTE(SUBSTITUTE(D43,"-","")," ","") -> 03376032437 | F43: =TRIM(PROPER(Raw_Data!E71)) -> Islamabad | G43: =TRIM(PROPER(Raw_Data!F71)) -> Smart Watch | H43: Electronics | I43: 46227 | J43: 5 | K43: 18000 | L43: =J43*K43 -> 90000 | M43: JazzCash | N43: InActive | O43: 46233 | P43: =LEFT(A43,3) -> ORD | Q43: =RIGHT(A43,4) -> 1067 | R43: =FIND("-",A43) -> 4 | S43: =MID(A43,FIND("-",A43)+1,4) -> 1067
A44: ORD-1067 | B44: =CLEAN(TRIM(Raw_Data!B78)) -> Amna Baig | C44: amna.baig@hotmail.com | D44: 0337-6032437 | E44: =SUBSTITUTE(SUBSTITUTE(D44,"-","")," ","") -> 03376032437 | F44: =TRIM(PROPER(Raw_Data!E78)) -> Islamabad | G44: =TRIM(PROPER(Raw_Data!F78)) -> Smart Watch | H44: Electronics | I44: 46227 | J44: 5 | K44: 18000 | L44: =J44*K44 -> 90000 | M44: JazzCash | N44: InActive | O44: 46233 | P44: =LEFT(A44,3) -> ORD | Q44: =RIGHT(A44,4) -> 1067 | R44: =FIND("-",A44) -> 4 | S44: =MID(A44,FIND("-",A44)+1,4) -> 1067
A45: ORD-1087 | B45: =CLEAN(TRIM(Raw_Data!B92)) -> Junaid Chaudhry | C45: junaid.chaudhry@yahoo.com | D45: 0344 7394713 | E45: =SUBSTITUTE(SUBSTITUTE(D45,"-","")," ","") -> 03447394713 | F45: =TRIM(PROPER(Raw_Data!E92)) -> Peshawar | G45: =TRIM(PROPER(Raw_Data!F92)) -> Handbag | H45: Accessories | I45: 46223 | J45: 2 | K45: 45000 | L45: =J45*K45 -> 90000 | M45: Cash | N45: InActive | O45: 46230 | P45: =LEFT(A45,3) -> ORD | Q45: =RIGHT(A45,4) -> 1087 | R45: =FIND("-",A45) -> 4 | S45: =MID(A45,FIND("-",A45)+1,4) -> 1087
A46: ORD-1096 | B46: =CLEAN(TRIM(Raw_Data!B101)) -> Sana Aslam | C46: sana.aslam@gmail.com | D46: 0397-5525929 | E46: =SUBSTITUTE(SUBSTITUTE(D46,"-","")," ","") -> 03975525929 | F46: =TRIM(PROPER(Raw_Data!E101)) -> Islamabad | G46: =TRIM(PROPER(Raw_Data!F101)) -> Vacuum Cleaner | H46: Home Appliances | I46: 46209 | J46: 5 | K46: 18000 | L46: =J46*K46 -> 90000 | M46: Not Specified | N46: InActive | O46: 46215 | P46: =LEFT(A46,3) -> ORD | Q46: =RIGHT(A46,4) -> 1096 | R46: =FIND("-",A46) -> 4 | S46: =MID(A46,FIND("-",A46)+1,4) -> 1096
A47: ORD-1054 | B47: =CLEAN(TRIM(Raw_Data!B57)) -> Asad Rana | C47: asad.rana@hotmail.com | D47: 03088867190 | E47: =SUBSTITUTE(SUBSTITUTE(D47,"-","")," ","") -> 03088867190 | F47: =TRIM(PROPER(Raw_Data!E57)) -> Faisalabad | G47: =TRIM(PROPER(Raw_Data!F57)) -> Microwave Oven | H47: Home Appliances | I47: 46222 | J47: 1 | K47: 85000 | L47: =J47*K47 -> 85000 | M47: Cash | N47: InActive | O47: 46224 | P47: =LEFT(A47,3) -> ORD | Q47: =RIGHT(A47,4) -> 1054 | R47: =FIND("-",A47) -> 4 | S47: =MID(A47,FIND("-",A47)+1,4) -> 1054
A48: ORD-1098 | B48: =CLEAN(TRIM(Raw_Data!B103)) -> Ali Aslam | C48: ali.aslam@outlook.com | D48: 03833283789 | E48: =SUBSTITUTE(SUBSTITUTE(D48,"-","")," ","") -> 03833283789 | F48: =TRIM(PROPER(Raw_Data!E103)) -> Rawalpindi | G48: =TRIM(PROPER(Raw_Data!F103)) -> Handbag | H48: Accessories | I48: 46240 | J48: 3 | K48: 25000 | L48: =J48*K48 -> 75000 | M48: Credit Card | N48: InActive | O48: 46243 | P48: =LEFT(A48,3) -> ORD | Q48: =RIGHT(A48,4) -> 1098 | R48: =FIND("-",A48) -> 4 | S48: =MID(A48,FIND("-",A48)+1,4) -> 1098
A49: ORD-1047 | B49: =CLEAN(TRIM(Raw_Data!B50)) -> Rabia Awan | C49: rabia.awan@hotmail.com | D49: 0364-8217547 | E49: =SUBSTITUTE(SUBSTITUTE(D49,"-","")," ","") -> 03648217547 | F49: =TRIM(PROPER(Raw_Data!E50)) -> Karachi | G49: =TRIM(PROPER(Raw_Data!F50)) -> Sofa Set | H49: Furniture | I49: 46210 | J49: 4 | K49: 18000 | L49: =J49*K49 -> 72000 | M49: Credit Card | N49: Active | O49: 46214 | P49: =LEFT(A49,3) -> ORD | Q49: =RIGHT(A49,4) -> 1047 | R49: =FIND("-",A49) -> 4 | S49: =MID(A49,FIND("-",A49)+1,4) -> 1047
A50: ORD-1061 | B50: =CLEAN(TRIM(Raw_Data!B65)) -> Hira Malik | C50: hira.malik@outlook.com | D50: 0363-9993490 | E50: =SUBSTITUTE(SUBSTITUTE(D50,"-","")," ","") -> 03639993490 | F50: =TRIM(PROPER(Raw_Data!E65)) -> Rawalpindi | G50: =TRIM(PROPER(Raw_Data!F65)) -> Sunglasses | H50: Accessories | I50: 46246 | J50: 1 | K50: 65000 | L50: =J50*K50 -> 65000 | M50: Bank Transfer | N50: InActive | O50: 46253 | P50: =LEFT(A50,3) -> ORD | Q50: =RIGHT(A50,4) -> 1061 | R50: =FIND("-",A50) -> 4 | S50: =MID(A50,FIND("-",A50)+1,4) -> 1061
A51: ORD-1082 | B51: =CLEAN(TRIM(Raw_Data!B87)) -> Salman Chaudhry | C51: salman.chaudhry@hotmail.com | D51: 03613570027 | E51: =SUBSTITUTE(SUBSTITUTE(D51,"-","")," ","") -> 03613570027 | F51: =TRIM(PROPER(Raw_Data!E87)) -> Multan | G51: =TRIM(PROPER(Raw_Data!F87)) -> Blender | H51: Home Appliances | I51: 46247 | J51: 1 | K51: 65000 | L51: =J51*K51 -> 65000 | M51: JazzCash | N51: Active | O51: 46253 | P51: =LEFT(A51,3) -> ORD | Q51: =RIGHT(A51,4) -> 1082 | R51: =FIND("-",A51) -> 4 | S51: =MID(A51,FIND("-",A51)+1,4) -> 1082
A52: ORD-1028 | B52: =CLEAN(TRIM(Raw_Data!B29)) -> Zeeshan Farooq | C52: zeeshan.farooq@yahoo.com | D52: 0375 9801946 | E52: =SUBSTITUTE(SUBSTITUTE(D52,"-","")," ","") -> 03759801946 | F52: =TRIM(PROPER(Raw_Data!E29)) -> Karachi | G52: =TRIM(PROPER(Raw_Data!F29)) -> Jacket | H52: =TRIM(PROPER(Raw_Data!G29)) -> Apparel | I52: 46206 | J52: 5 | K52: 12000 | L52: =J52*K52 -> 60000 | M52: Cash | N52: Pending | O52: 46208 | P52: =LEFT(A52,3) -> ORD | Q52: =RIGHT(A52,4) -> 1028 | R52: =FIND("-",A52) -> 4 | S52: =MID(A52,FIND("-",A52)+1,4) -> 1028
A53: ORD-1048 | B53: =CLEAN(TRIM(Raw_Data!B51)) -> Faisal Ali | C53: faisal.ali@gmail.com | D53: 0316 2006313 | E53: =SUBSTITUTE(SUBSTITUTE(D53,"-","")," ","") -> 03162006313 | F53: =TRIM(PROPER(Raw_Data!E51)) -> Multan | G53: =TRIM(PROPER(Raw_Data!F51)) -> Jacket | H53: Apparel | I53: 46207 | J53: 5 | K53: 12000 | L53: =J53*K53 -> 60000 | M53: Bank Transfer | N53: InActive | O53: 46211 | P53: =LEFT(A53,3) -> ORD | Q53: =RIGHT(A53,4) -> 1048 | R53: =FIND("-",A53) -> 4 | S53: =MID(A53,FIND("-",A53)+1,4) -> 1048
A54: ORD-1065 | B54: =CLEAN(TRIM(Raw_Data!B69)) -> Hamza Javed | C54: hamza.javed@outlook.com | D54: 03097815076 | E54: =SUBSTITUTE(SUBSTITUTE(D54,"-","")," ","") -> 03097815076 | F54: =TRIM(PROPER(Raw_Data!E69)) -> Islamabad | G54: =TRIM(PROPER(Raw_Data!F69)) -> Water Dispenser | H54: Home Appliances | I54: 46253 | J54: 3 | K54: 18000 | L54: =J54*K54 -> 54000 | M54: Bank Transfer | N54: Active | O54: 46260 | P54: =LEFT(A54,3) -> ORD | Q54: =RIGHT(A54,4) -> 1065 | R54: =FIND("-",A54) -> 4 | S54: =MID(A54,FIND("-",A54)+1,4) -> 1065
A55: ORD-1039 | B55: =CLEAN(TRIM(Raw_Data!B41)) -> Nida Abbasi | C55: nida.abbasi@yahoo.com | D55: 03851157662 | E55: =SUBSTITUTE(SUBSTITUTE(D55,"-","")," ","") -> 03851157662 | F55: =TRIM(PROPER(Raw_Data!E41)) -> Islamabad | G55: =TRIM(PROPER(Raw_Data!F41)) -> Jacket | H55: =TRIM(PROPER(Raw_Data!G41)) -> Apparel | I55: 46233 | J55: 2 | K55: 25000 | L55: =J55*K55 -> 50000 | M55: JazzCash | N55: InActive | O55: 46237 | P55: =LEFT(A55,3) -> ORD | Q55: =RIGHT(A55,4) -> 1039 | R55: =FIND("-",A55) -> 4 | S55: =MID(A55,FIND("-",A55)+1,4) -> 1039
A56: ORD-1030 | B56: =CLEAN(TRIM(Raw_Data!B32)) -> Asad Chaudhry | C56: asad.chaudhry@outlook.com | D56: 0394-2664863 | E56: =SUBSTITUTE(SUBSTITUTE(D56,"-","")," ","") -> 03942664863 | F56: =TRIM(PROPER(Raw_Data!E32)) -> Faisalabad | G56: =TRIM(PROPER(Raw_Data!F32)) -> Sofa Set | H56: =TRIM(PROPER(Raw_Data!G32)) -> Furniture | I56: 46248 | J56: 4 | K56: 12000 | L56: =J56*K56 -> 48000 | M56: Cash | N56: Pending | O56: 46254 | P56: =LEFT(A56,3) -> ORD | Q56: =RIGHT(A56,4) -> 1030 | R56: =FIND("-",A56) -> 4 | S56: =MID(A56,FIND("-",A56)+1,4) -> 1030
A57: ORD-1093 | B57: =CLEAN(TRIM(Raw_Data!B98)) -> Zainab Ahmed | C57: zainab.ahmed@outlook.com | D57: 0389-3875339 | E57: =SUBSTITUTE(SUBSTITUTE(D57,"-","")," ","") -> 03893875339 | F57: =TRIM(PROPER(Raw_Data!E98)) -> Peshawar | G57: =TRIM(PROPER(Raw_Data!F98)) -> Air Fryer | H57: Home Appliances | I57: 46248 | J57: 4 | K57: 12000 | L57: =J57*K57 -> 48000 | M57: Cash | N57: Pending | O57: 46254 | P57: =LEFT(A57,3) -> ORD | Q57: =RIGHT(A57,4) -> 1093 | R57: =FIND("-",A57) -> 4 | S57: =MID(A57,FIND("-",A57)+1,4) -> 1093
A58: ORD-1089 | B58: =CLEAN(TRIM(Raw_Data!B49)) -> Ali Raza | C58: ali.raza@gmail.com | D58: 03894431161 | E58: =SUBSTITUTE(SUBSTITUTE(D58,"-","")," ","") -> 03894431161 | F58: =TRIM(PROPER(Raw_Data!E49)) -> Multan | G58: =TRIM(PROPER(Raw_Data!F49)) -> Vacuum Cleaner | H58: Home Appliances | I58: 46235 | J58: 1 | K58: 45000 | L58: =J58*K58 -> 45000 | M58: Bank Transfer | N58: Active | O58: 46240 | P58: =LEFT(A58,3) -> ORD | Q58: =RIGHT(A58,4) -> 1089 | R58: =FIND("-",A58) -> 4 | S58: =MID(A58,FIND("-",A58)+1,4) -> 1089
A59: ORD-1099 | B59: =CLEAN(TRIM(Raw_Data!B104)) -> Naveed Raza | C59: naveed.raza@yahoo.com | D59: 03594517316 | E59: =SUBSTITUTE(SUBSTITUTE(D59,"-","")," ","") -> 03594517316 | F59: =TRIM(PROPER(Raw_Data!E104)) -> Karachi | G59: =TRIM(PROPER(Raw_Data!F104)) -> Led Tv | H59: Electronics | I59: 46231 | J59: 1 | K59: 45000 | L59: =J59*K59 -> 45000 | M59: Cash | N59: InActive | O59: 46236 | P59: =LEFT(A59,3) -> ORD | Q59: =RIGHT(A59,4) -> 1099 | R59: =FIND("-",A59) -> 4 | S59: =MID(A59,FIND("-",A59)+1,4) -> 1099
A60: ORD-1019 | B60: =CLEAN(TRIM(Raw_Data!B20)) -> Faisal Awan | C60: faisal.awan@gmail.com | D60: 03917442089 | E60: =SUBSTITUTE(SUBSTITUTE(D60,"-","")," ","") -> 03917442089 | F60: =TRIM(PROPER(Raw_Data!E20)) -> Islamabad | G60: =TRIM(PROPER(Raw_Data!F20)) -> Smart Watch | H60: =TRIM(PROPER(Raw_Data!G20)) -> Electronics | I60: 46233 | J60: 5 | K60: 8500 | L60: =J60*K60 -> 42500 | M60: Cash | N60: Pending | O60: 46235 | P60: =LEFT(A60,3) -> ORD | Q60: =RIGHT(A60,4) -> 1019 | R60: =FIND("-",A60) -> 4 | S60: =MID(A60,FIND("-",A60)+1,4) -> 1019
A61: ORD-1042 | B61: =CLEAN(TRIM(Raw_Data!B44)) -> Tariq Aslam | C61: tariq.aslam@hotmail.com | D61: 03158630043 | E61: =SUBSTITUTE(SUBSTITUTE(D61,"-","")," ","") -> 03158630043 | F61: =TRIM(PROPER(Raw_Data!E44)) -> Faisalabad | G61: =TRIM(PROPER(Raw_Data!F44)) -> Jacket | H61: =TRIM(PROPER(Raw_Data!G44)) -> Apparel | I61: 46239 | J61: 5 | K61: 8500 | L61: =J61*K61 -> 42500 | M61: Cash | N61: InActive | O61: 46243 | P61: =LEFT(A61,3) -> ORD | Q61: =RIGHT(A61,4) -> 1042 | R61: =FIND("-",A61) -> 4 | S61: =MID(A61,FIND("-",A61)+1,4) -> 1042
A62: ORD-1051 | B62: =CLEAN(TRIM(Raw_Data!B54)) -> Sadia Malik | C62: sadia.malik@outlook.com | D62: 0376-1919088 | E62: =SUBSTITUTE(SUBSTITUTE(D62,"-","")," ","") -> 03761919088 | F62: =TRIM(PROPER(Raw_Data!E54)) -> Rawalpindi | G62: =TRIM(PROPER(Raw_Data!F54)) -> Running Shoes | H62: Apparel | I62: 46212 | J62: 5 | K62: 8500 | L62: =J62*K62 -> 42500 | M62: JazzCash | N62: Pending | O62: 46217 | P62: =LEFT(A62,3) -> ORD | Q62: =RIGHT(A62,4) -> 1051 | R62: =FIND("-",A62) -> 4 | S62: =MID(A62,FIND("-",A62)+1,4) -> 1051
A63: ORD-1088 | B63: =CLEAN(TRIM(Raw_Data!B93)) -> Hassan Aslam | C63: rabia.anwar@outlook.com | D63: 0347 2551288 | E63: =SUBSTITUTE(SUBSTITUTE(D63,"-","")," ","") -> 03472551288 | F63: =TRIM(PROPER(Raw_Data!E93)) -> Rawalpindi | G63: =TRIM(PROPER(Raw_Data!F93)) -> Water Dispenser | H63: Unknown | I63: 46241 | J63: 5 | K63: 8500 | L63: =J63*K63 -> 42500 | M63: JazzCash | N63: Active | O63: 46248 | P63: =LEFT(A63,3) -> ORD | Q63: =RIGHT(A63,4) -> 1088 | R63: =FIND("-",A63) -> 4 | S63: =MID(A63,FIND("-",A63)+1,4) -> 1088
A64: ORD-1055 | B64: =CLEAN(TRIM(Raw_Data!B58)) -> Hamza Baig | C64: hamza.baig@yahoo.com | D64: 0307-8558523 | E64: =SUBSTITUTE(SUBSTITUTE(D64,"-","")," ","") -> 03078558523 | F64: =TRIM(PROPER(Raw_Data!E58)) -> Multan | G64: =TRIM(PROPER(Raw_Data!F58)) -> Office Chair | H64: Furniture | I64: 46237 | J64: 2 | K64: 18000 | L64: =J64*K64 -> 36000 | M64: Bank Transfer | N64: InActive | O64: 46243 | P64: =LEFT(A64,3) -> ORD | Q64: =RIGHT(A64,4) -> 1055 | R64: =FIND("-",A64) -> 4 | S64: =MID(A64,FIND("-",A64)+1,4) -> 1055
A65: ORD-1008 | B65: =CLEAN(TRIM(Raw_Data!B9)) -> Rida Iqbal | C65: rida.iqbal@gmail.com | D65: 0304-6543670 | E65: =SUBSTITUTE(SUBSTITUTE(D65,"-","")," ","") -> 03046543670 | F65: =TRIM(PROPER(Raw_Data!E9)) -> Faisalabad | G65: =TRIM(PROPER(Raw_Data!F9)) -> Vacuum Cleaner | H65: =TRIM(PROPER(Raw_Data!G9)) -> Home Appliances | I65: 46219 | J65: 4 | K65: 8500 | L65: =J65*K65 -> 34000 | M65: Cash | N65: InActive | O65: 46224 | P65: =LEFT(A65,3) -> ORD | Q65: =RIGHT(A65,4) -> 1008 | R65: =FIND("-",A65) -> 4 | S65: =MID(A65,FIND("-",A65)+1,4) -> 1008
A66: ORD-1071 | B66: =CLEAN(TRIM(Raw_Data!B75)) -> Faisal Baig | C66: faisal.baig@yahoo.com | D66: 0344-7689354 | E66: =SUBSTITUTE(SUBSTITUTE(D66,"-","")," ","") -> 03447689354 | F66: =TRIM(PROPER(Raw_Data!E75)) -> Karachi | G66: =TRIM(PROPER(Raw_Data!F75)) -> Smart Watch | H66: Electronics | I66: 46228 | J66: 4 | K66: 8500 | L66: =J66*K66 -> 34000 | M66: Cash | N66: InActive | O66: 46234 | P66: =LEFT(A66,3) -> ORD | Q66: =RIGHT(A66,4) -> 1071 | R66: =FIND("-",A66) -> 4 | S66: =MID(A66,FIND("-",A66)+1,4) -> 1071
A67: ORD-1011 | B67: =CLEAN(TRIM(Raw_Data!B12)) -> Anum Sheikh | C67: anum.sheikh@gmail.com | D67: 0330-7774229 | E67: =SUBSTITUTE(SUBSTITUTE(D67,"-","")," ","") -> 03307774229 | F67: =TRIM(PROPER(Raw_Data!E12)) -> Rawalpindi | G67: =TRIM(PROPER(Raw_Data!F12)) -> Water Dispenser | H67: =TRIM(PROPER(Raw_Data!G12)) -> Home Appliances | I67: 46220 | J67: 3 | K67: 8500 | L67: =J67*K67 -> 25500 | M67: Credit Card | N67: Pending | O67: 46223 | P67: =LEFT(A67,3) -> ORD | Q67: =RIGHT(A67,4) -> 1011 | R67: =FIND("-",A67) -> 4 | S67: =MID(A67,FIND("-",A67)+1,4) -> 1011
A68: ORD-1018 | B68: =CLEAN(TRIM(Raw_Data!B19)) -> Ali Chaudhry | C68: ali.chaudhry@outlook.com | D68: 0356 8418210 | E68: =SUBSTITUTE(SUBSTITUTE(D68,"-","")," ","") -> 03568418210 | F68: =TRIM(PROPER(Raw_Data!E19)) -> Sialkot | G68: =TRIM(PROPER(Raw_Data!F19)) -> Headphones | H68: =TRIM(PROPER(Raw_Data!G19)) -> Electronics | I68: 46252 | J68: 3 | K68: 8500 | L68: =J68*K68 -> 25500 | M68: Credit Card | N68: Active | O68: 46255 | P68: =LEFT(A68,3) -> ORD | Q68: =RIGHT(A68,4) -> 1018 | R68: =FIND("-",A68) -> 4 | S68: =MID(A68,FIND("-",A68)+1,4) -> 1018
A69: ORD-1044 | B69: =CLEAN(TRIM(Raw_Data!B46)) -> Komal Raza | C69: komal.raza@yahoo.com | D69: 0369-7017548 | E69: =SUBSTITUTE(SUBSTITUTE(D69,"-","")," ","") -> 03697017548 | F69: =TRIM(PROPER(Raw_Data!E46)) -> Rawalpindi | G69: =TRIM(PROPER(Raw_Data!F46)) -> Wrist Watch | H69: =TRIM(PROPER(Raw_Data!G46)) -> Accessories | I69: 46205 | J69: 3 | K69: 8500 | L69: =J69*K69 -> 25500 | M69: Cash | N69: Active | O69: 46207 | P69: =LEFT(A69,3) -> ORD | Q69: =RIGHT(A69,4) -> 1044 | R69: =FIND("-",A69) -> 4 | S69: =MID(A69,FIND("-",A69)+1,4) -> 1044
A70: ORD-1086 | B70: =CLEAN(TRIM(Raw_Data!B91)) -> Bilal Malik | C70: Not Provided | D70: 03941742169 | E70: =SUBSTITUTE(SUBSTITUTE(D70,"-","")," ","") -> 03941742169 | F70: =TRIM(PROPER(Raw_Data!E91)) -> Rawalpindi | G70: =TRIM(PROPER(Raw_Data!F91)) -> Running Shoes | H70: Apparel | I70: 46242 | J70: 3 | K70: 8500 | L70: =J70*K70 -> 25500 | M70: Credit Card | N70: Pending | O70: 46249 | P70: =LEFT(A70,3) -> ORD | Q70: =RIGHT(A70,4) -> 1086 | R70: =FIND("-",A70) -> 4 | S70: =MID(A70,FIND("-",A70)+1,4) -> 1086
A71: ORD-1095 | B71: =CLEAN(TRIM(Raw_Data!B100)) -> Sadia Iqbal | C71: sadia.iqbal@hotmail.com | D71: 0399-6475691 | E71: =SUBSTITUTE(SUBSTITUTE(D71,"-","")," ","") -> 03996475691 | F71: =TRIM(PROPER(Raw_Data!E100)) -> Sialkot | G71: =TRIM(PROPER(Raw_Data!F100)) -> Vacuum Cleaner | H71: Home Appliances | I71: 46209 | J71: 3 | K71: 8500 | L71: =J71*K71 -> 25500 | M71: Cash | N71: Active | O71: 46215 | P71: =LEFT(A71,3) -> ORD | Q71: =RIGHT(A71,4) -> 1095 | R71: =FIND("-",A71) -> 4 | S71: =MID(A71,FIND("-",A71)+1,4) -> 1095
A72: ORD-1052 | B72: =CLEAN(TRIM(Raw_Data!B55)) -> Bilal Aslam | C72: bilal.aslam@gmail.com | D72: 0340 8202195 | E72: =SUBSTITUTE(SUBSTITUTE(D72,"-","")," ","") -> 03408202195 | F72: =TRIM(PROPER(Raw_Data!E55)) -> Peshawar | G72: =TRIM(PROPER(Raw_Data!F55)) -> Laptop | H72: Electronics | I72: 46248 | J72: 1 | K72: 25000 | L72: =J72*K72 -> 25000 | M72: Cash | N72: InActive | O72: 46252 | P72: =LEFT(A72,3) -> ORD | Q72: =RIGHT(A72,4) -> 1052 | R72: =FIND("-",A72) -> 4 | S72: =MID(A72,FIND("-",A72)+1,4) -> 1052
A73: ORD-1059 | B73: =CLEAN(TRIM(Raw_Data!B63)) -> Umar Butt | C73: umar.butt@gmail.com | D73: 0313-9655523 | E73: =SUBSTITUTE(SUBSTITUTE(D73,"-","")," ","") -> 03139655523 | F73: =TRIM(PROPER(Raw_Data!E63)) -> Islamabad | G73: =TRIM(PROPER(Raw_Data!F63)) -> Microwave Oven | H73: Home Appliances | I73: 46232 | J73: 1 | K73: 25000 | L73: =J73*K73 -> 25000 | M73: Cash | N73: Active | O73: 46236 | P73: =LEFT(A73,3) -> ORD | Q73: =RIGHT(A73,4) -> 1059 | R73: =FIND("-",A73) -> 4 | S73: =MID(A73,FIND("-",A73)+1,4) -> 1059
A74: ORD-1045 | B74: =CLEAN(TRIM(Raw_Data!B47)) -> Rida Raza | C74: rida.raza@yahoo.com | D74: 0300-5651899 | E74: =SUBSTITUTE(SUBSTITUTE(D74,"-","")," ","") -> 03005651899 | F74: =TRIM(PROPER(Raw_Data!E47)) -> Faisalabad | G74: =TRIM(PROPER(Raw_Data!F47)) -> Laptop | H74: Unknown | I74: 46224 | J74: 2 | K74: 12000 | L74: =J74*K74 -> 24000 | M74: Cash | N74: InActive | O74: 46226 | P74: =LEFT(A74,3) -> ORD | Q74: =RIGHT(A74,4) -> 1045 | R74: =FIND("-",A74) -> 4 | S74: =MID(A74,FIND("-",A74)+1,4) -> 1045
A75: ORD-1063 | B75: =CLEAN(TRIM(Raw_Data!B67)) -> Hassan Ali | C75: hassan.ali@outlook.com | D75: 03056294819 | E75: =SUBSTITUTE(SUBSTITUTE(D75,"-","")," ","") -> 03056294819 | F75: Unknown | G75: =TRIM(PROPER(Raw_Data!F67)) -> Study Table | H75: Furniture | I75: 46225 | J75: 1 | K75: 18000 | L75: =J75*K75 -> 18000 | M75: Bank Transfer | N75: Pending | O75: 46229 | P75: =LEFT(A75,3) -> ORD | Q75: =RIGHT(A75,4) -> 1063 | R75: =FIND("-",A75) -> 4 | S75: =MID(A75,FIND("-",A75)+1,4) -> 1063
A76: ORD-1014 | B76: =CLEAN(TRIM(Raw_Data!B15)) -> Mahnoor Ali | C76: mahnoor.ali@yahoo.com | D76: Not Provided | E76: =SUBSTITUTE(SUBSTITUTE(D76,"-","")," ","") -> NotProvided | F76: =TRIM(PROPER(Raw_Data!E15)) -> Multan | G76: =TRIM(PROPER(Raw_Data!F15)) -> Study Table | H76: =TRIM(PROPER(Raw_Data!G15)) -> Furniture | I76: 46230 | J76: 2 | K76: 8500 | L76: =J76*K76 -> 17000 | M76: Cash | N76: Pending | O76: 46236 | P76: =LEFT(A76,3) -> ORD | Q76: =RIGHT(A76,4) -> 1014 | R76: =FIND("-",A76) -> 4 | S76: =MID(A76,FIND("-",A76)+1,4) -> 1014
A77: ORD-1023 | B77: =CLEAN(TRIM(Raw_Data!B24)) -> Kashif Aslam | C77: kashif.aslam@outlook.com | D77: 03968072684 | E77: =SUBSTITUTE(SUBSTITUTE(D77,"-","")," ","") -> 03968072684 | F77: =TRIM(PROPER(Raw_Data!E24)) -> Sialkot | G77: =TRIM(PROPER(Raw_Data!F24)) -> Mobile Phone | H77: =TRIM(PROPER(Raw_Data!G24)) -> Electronics | I77: 46206 | J77: 2 | K77: 8500 | L77: =J77*K77 -> 17000 | M77: Cash | N77: Active | O77: 46208 | P77: =LEFT(A77,3) -> ORD | Q77: =RIGHT(A77,4) -> 1023 | R77: =FIND("-",A77) -> 4 | S77: =MID(A77,FIND("-",A77)+1,4) -> 1023
A78: ORD-1079 | B78: =CLEAN(TRIM(Raw_Data!B84)) -> Fahad Qureshi | C78: fahad.qureshi@outlook.com | D78: 0341 5788474 | E78: =SUBSTITUTE(SUBSTITUTE(D78,"-","")," ","") -> 03415788474 | F78: =TRIM(PROPER(Raw_Data!E84)) -> Karachi | G78: =TRIM(PROPER(Raw_Data!F84)) -> Mobile Phone | H78: Electronics | I78: 46206 | J78: 4 | K78: 4000 | L78: =J78*K78 -> 16000 | M78: Credit Card | N78: Active | O78: 46211 | P78: =LEFT(A78,3) -> ORD | Q78: =RIGHT(A78,4) -> 1079 | R78: =FIND("-",A78) -> 4 | S78: =MID(A78,FIND("-",A78)+1,4) -> 1079
A79: ORD-1013 | B79: =CLEAN(TRIM(Raw_Data!B14)) -> Usman Butt | C79: usman.butt@gmail.com | D79: 0326-6752576 | E79: =SUBSTITUTE(SUBSTITUTE(D79,"-","")," ","") -> 03266752576 | F79: =TRIM(PROPER(Raw_Data!E14)) -> Faisalabad | G79: =TRIM(PROPER(Raw_Data!F14)) -> Mobile Phone | H79: =TRIM(PROPER(Raw_Data!G14)) -> Electronics | I79: 46225 | J79: 3 | K79: 4000 | L79: =J79*K79 -> 12000 | M79: JazzCash | N79: InActive | O79: 46228 | P79: =LEFT(A79,3) -> ORD | Q79: =RIGHT(A79,4) -> 1013 | R79: =FIND("-",A79) -> 4 | S79: =MID(A79,FIND("-",A79)+1,4) -> 1013
A80: ORD-1056 | B80: =CLEAN(TRIM(Raw_Data!B59)) -> Maryam Awan | C80: maryam.awan@hotmail.com | D80: 0336 5227787 | E80: =SUBSTITUTE(SUBSTITUTE(D80,"-","")," ","") -> 03365227787 | F80: =TRIM(PROPER(Raw_Data!E59)) -> Islamabad | G80: =TRIM(PROPER(Raw_Data!F59)) -> Led Tv | H80: Electronics | I80: 46212 | J80: 1 | K80: 12000 | L80: =J80*K80 -> 12000 | M80: JazzCash | N80: Pending | O80: 46218 | P80: =LEFT(A80,3) -> ORD | Q80: =RIGHT(A80,4) -> 1056 | R80: =FIND("-",A80) -> 4 | S80: =MID(A80,FIND("-",A80)+1,4) -> 1056
A81: ORD-1073 | B81: =CLEAN(TRIM(Raw_Data!B77)) -> Farah Javed | C81: farah.javed@gmail.com | D81: 0309 7481857 | E81: =SUBSTITUTE(SUBSTITUTE(D81,"-","")," ","") -> 03097481857 | F81: =TRIM(PROPER(Raw_Data!E77)) -> Faisalabad | G81: =TRIM(PROPER(Raw_Data!F77)) -> Smart Watch | H81: Electronics | I81: 46225 | J81: 3 | K81: 4000 | L81: =J81*K81 -> 12000 | M81: Credit Card | N81: InActive | O81: 46231 | P81: =LEFT(A81,3) -> ORD | Q81: =RIGHT(A81,4) -> 1073 | R81: =FIND("-",A81) -> 4 | S81: =MID(A81,FIND("-",A81)+1,4) -> 1073
A82: ORD-1007 | B82: =CLEAN(TRIM(Raw_Data!B8)) -> Bushra Ali | C82: bushra.ali@yahoo.com | D82: 0333 9852897 | E82: =SUBSTITUTE(SUBSTITUTE(D82,"-","")," ","") -> 03339852897 | F82: =TRIM(PROPER(Raw_Data!E8)) -> Rawalpindi | G82: =TRIM(PROPER(Raw_Data!F8)) -> Study Table | H82: =TRIM(PROPER(Raw_Data!G8)) -> Furniture | I82: 46232 | J82: 4 | K82: 2500 | L82: =J82*K82 -> 10000 | M82: Credit Card | N82: Unknown | O82: 46238 | P82: =LEFT(A82,3) -> ORD | Q82: =RIGHT(A82,4) -> 1007 | R82: =FIND("-",A82) -> 4 | S82: =MID(A82,FIND("-",A82)+1,4) -> 1007
A83: ORD-1020 | B83: =CLEAN(TRIM(Raw_Data!B21)) -> Anum Siddiqui | C83: anum.siddiqui@outlook.com | D83: 0370-8481188 | E83: =SUBSTITUTE(SUBSTITUTE(D83,"-","")," ","") -> 03708481188 | F83: =TRIM(PROPER(Raw_Data!E21)) -> Sialkot | G83: =TRIM(PROPER(Raw_Data!F21)) -> Sofa Set | H83: =TRIM(PROPER(Raw_Data!G21)) -> Furniture | I83: 46219 | J83: 4 | K83: 2500 | L83: =J83*K83 -> 10000 | M83: Credit Card | N83: Active | O83: 46223 | P83: =LEFT(A83,3) -> ORD | Q83: =RIGHT(A83,4) -> 1020 | R83: =FIND("-",A83) -> 4 | S83: =MID(A83,FIND("-",A83)+1,4) -> 1020
A84: ORD-1031 | B84: =CLEAN(TRIM(Raw_Data!B33)) -> Noor Ali | C84: noor.ali@hotmail.com | D84: 0325-8132648 | E84: =SUBSTITUTE(SUBSTITUTE(D84,"-","")," ","") -> 03258132648 | F84: =TRIM(PROPER(Raw_Data!E33)) -> Islamabad | G84: =TRIM(PROPER(Raw_Data!F33)) -> Headphones | H84: =TRIM(PROPER(Raw_Data!G33)) -> Electronics | I84: 46240 | J84: 4 | K84: 2500 | L84: =J84*K84 -> 10000 | M84: JazzCash | N84: Pending | O84: 46244 | P84: =LEFT(A84,3) -> ORD | Q84: =RIGHT(A84,4) -> 1031 | R84: =FIND("-",A84) -> 4 | S84: =MID(A84,FIND("-",A84)+1,4) -> 1031
A85: ORD-1032 | B85: =CLEAN(TRIM(Raw_Data!B34)) -> Rabia Anwar | C85: rabia.anwar@outlook.com | D85: 0341-5200476 | E85: =SUBSTITUTE(SUBSTITUTE(D85,"-","")," ","") -> 03415200476 | F85: =TRIM(PROPER(Raw_Data!E34)) -> Lahore | G85: =TRIM(PROPER(Raw_Data!F34)) -> Office Chair | H85: =TRIM(PROPER(Raw_Data!G34)) -> Furniture | I85: 46241 | J85: 4 | K85: 2500 | L85: =J85*K85 -> 10000 | M85: JazzCash | N85: Active | O85: 46246 | P85: =LEFT(A85,3) -> ORD | Q85: =RIGHT(A85,4) -> 1032 | R85: =FIND("-",A85) -> 4 | S85: =MID(A85,FIND("-",A85)+1,4) -> 1032
A86: ORD-1046 | B86: =CLEAN(TRIM(Raw_Data!B48)) -> Bilal Abbasi | C86: bilal.abbasi@hotmail.com | D86: 0378 1727544 | E86: =SUBSTITUTE(SUBSTITUTE(D86,"-","")," ","") -> 03781727544 | F86: =TRIM(PROPER(Raw_Data!E48)) -> Faisalabad | G86: =TRIM(PROPER(Raw_Data!F48)) -> Laptop | H86: Electronics | I86: 46210 | J86: 4 | K86: 2500 | L86: =J86*K86 -> 10000 | M86: Cash | N86: Active | O86: 46215 | P86: =LEFT(A86,3) -> ORD | Q86: =RIGHT(A86,4) -> 1046 | R86: =FIND("-",A86) -> 4 | S86: =MID(A86,FIND("-",A86)+1,4) -> 1046
A87: ORD-1100 | B87: =CLEAN(TRIM(Raw_Data!B105)) -> Junaid Siddiqui | C87: junaid.siddiqui@hotmail.com | D87: 0310-2834914 | E87: =SUBSTITUTE(SUBSTITUTE(D87,"-","")," ","") -> 03102834914 | F87: =TRIM(PROPER(Raw_Data!E105)) -> Multan | G87: =TRIM(PROPER(Raw_Data!F105)) -> Mobile Phone | H87: Electronics | I87: 46252 | J87: 4 | K87: 2500 | L87: =J87*K87 -> 10000 | M87: Cash | N87: Active | O87: 46256 | P87: =LEFT(A87,3) -> ORD | Q87: =RIGHT(A87,4) -> 1100 | R87: =FIND("-",A87) -> 4 | S87: =MID(A87,FIND("-",A87)+1,4) -> 1100
A88: ORD-1033 | B88: =CLEAN(TRIM(Raw_Data!B35)) -> Usman Sheikh | C88: usman.sheikh@outlook.com | D88: 03701615675 | E88: =SUBSTITUTE(SUBSTITUTE(D88,"-","")," ","") -> 03701615675 | F88: =TRIM(PROPER(Raw_Data!E35)) -> Faisalabad | G88: =TRIM(PROPER(Raw_Data!F35)) -> Handbag | H88: =TRIM(PROPER(Raw_Data!G35)) -> Accessories | I88: 46233 | J88: 1 | K88: 8500 | L88: =J88*K88 -> 8500 | M88: JazzCash | N88: Pending | O88: 46238 | P88: =LEFT(A88,3) -> ORD | Q88: =RIGHT(A88,4) -> 1033 | R88: =FIND("-",A88) -> 4 | S88: =MID(A88,FIND("-",A88)+1,4) -> 1033
A89: ORD-1038 | B89: =CLEAN(TRIM(Raw_Data!B40)) -> Nida Chaudhry | C89: nida.chaudhry@gmail.com | D89: 0312-8443690 | E89: =SUBSTITUTE(SUBSTITUTE(D89,"-","")," ","") -> 03128443690 | F89: =TRIM(PROPER(Raw_Data!E40)) -> Lahore | G89: =TRIM(PROPER(Raw_Data!F40)) -> Mobile Phone | H89: =TRIM(PROPER(Raw_Data!G40)) -> Electronics | I89: 46230 | J89: 2 | K89: 4000 | L89: =J89*K89 -> 8000 | M89: Cash | N89: Pending | O89: 46236 | P89: =LEFT(A89,3) -> ORD | Q89: =RIGHT(A89,4) -> 1038 | R89: =FIND("-",A89) -> 4 | S89: =MID(A89,FIND("-",A89)+1,4) -> 1038
A90: ORD-1005 | B90: =CLEAN(TRIM(Raw_Data!B6)) -> Zainab Ahmed | C90: zainab.ahmed@yahoo.com | D90: 03087455324 | E90: =SUBSTITUTE(SUBSTITUTE(D90,"-","")," ","") -> 03087455324 | F90: =TRIM(PROPER(Raw_Data!E6)) -> Sialkot | G90: =TRIM(PROPER(Raw_Data!F6)) -> Vacuum Cleaner | H90: =TRIM(PROPER(Raw_Data!G6)) -> Home Appliances | I90: 46252 | J90: 3 | K90: 2500 | L90: =J90*K90 -> 7500 | M90: Credit Card | N90: Unknown | O90: 46256 | P90: =LEFT(A90,3) -> ORD | Q90: =RIGHT(A90,4) -> 1005 | R90: =FIND("-",A90) -> 4 | S90: =MID(A90,FIND("-",A90)+1,4) -> 1005
A91: ORD-1010 | B91: =CLEAN(TRIM(Raw_Data!B11)) -> Nida Sheikh | C91: nida.sheikh@outlook.com | D91: 03481036161 | E91: =SUBSTITUTE(SUBSTITUTE(D91,"-","")," ","") -> 03481036161 | F91: =TRIM(PROPER(Raw_Data!E11)) -> Sialkot | G91: =TRIM(PROPER(Raw_Data!F11)) -> Vacuum Cleaner | H91: =TRIM(PROPER(Raw_Data!G11)) -> Home Appliances | I91: 46207 | J91: 5 | K91: 1500 | L91: =J91*K91 -> 7500 | M91: Bank Transfer | N91: InActive | O91: 46213 | P91: =LEFT(A91,3) -> ORD | Q91: =RIGHT(A91,4) -> 1010 | R91: =FIND("-",A91) -> 4 | S91: =MID(A91,FIND("-",A91)+1,4) -> 1010
A92: ORD-1072 | B92: =CLEAN(TRIM(Raw_Data!B30)) -> Zeeshan Sheikh | C92: Not Provided | D92: 03509479950 | E92: =SUBSTITUTE(SUBSTITUTE(D92,"-","")," ","") -> 03509479950 | F92: =TRIM(PROPER(Raw_Data!E30)) -> Rawalpindi | G92: =TRIM(PROPER(Raw_Data!F30)) -> Mobile Phone | H92: =TRIM(PROPER(Raw_Data!G30)) -> Electronics | I92: 46234 | J92: 5 | K92: 1500 | L92: =J92*K92 -> 7500 | M92: Cash | N92: Active | O92: 46238 | P92: =LEFT(A92,3) -> ORD | Q92: =RIGHT(A92,4) -> 1072 | R92: =FIND("-",A92) -> 4 | S92: =MID(A92,FIND("-",A92)+1,4) -> 1072
A93: ORD-1041 | B93: =CLEAN(TRIM(Raw_Data!B43)) -> Asad Ahmed | C93: asad.ahmed@yahoo.com | D93: 0322-4368777 | E93: =SUBSTITUTE(SUBSTITUTE(D93,"-","")," ","") -> 03224368777 | F93: =TRIM(PROPER(Raw_Data!E43)) -> Multan | G93: =TRIM(PROPER(Raw_Data!F43)) -> Bookshelf | H93: =TRIM(PROPER(Raw_Data!G43)) -> Furniture | I93: 46222 | J93: 3 | K93: 2500 | L93: =J93*K93 -> 7500 | M93: JazzCash | N93: Active | O93: 46229 | P93: =LEFT(A93,3) -> ORD | Q93: =RIGHT(A93,4) -> 1041 | R93: =FIND("-",A93) -> 4 | S93: =MID(A93,FIND("-",A93)+1,4) -> 1041
A94: ORD-1072 | B94: =CLEAN(TRIM(Raw_Data!B76)) -> Zeeshan Sheikh | C94: Not Provided | D94: 03509479950 | E94: =SUBSTITUTE(SUBSTITUTE(D94,"-","")," ","") -> 03509479950 | F94: =TRIM(PROPER(Raw_Data!E76)) -> Rawalpindi | G94: =TRIM(PROPER(Raw_Data!F76)) -> Mobile Phone | H94: Electronics | I94: 46234 | J94: 5 | K94: 1500 | L94: =J94*K94 -> 7500 | M94: Cash | N94: Active | O94: 46238 | P94: =LEFT(A94,3) -> ORD | Q94: =RIGHT(A94,4) -> 1072 | R94: =FIND("-",A94) -> 4 | S94: =MID(A94,FIND("-",A94)+1,4) -> 1072
A95: ORD-1094 | B95: =CLEAN(TRIM(Raw_Data!B99)) -> Danish Rana | C95: danish.rana@yahoo.com | D95: 0375 3419132 | E95: =SUBSTITUTE(SUBSTITUTE(D95,"-","")," ","") -> 03753419132 | F95: =TRIM(PROPER(Raw_Data!E99)) -> Karachi | G95: =TRIM(PROPER(Raw_Data!F99)) -> Sofa Set | H95: Furniture | I95: 46225 | J95: 2 | K95: 2500 | L95: =J95*K95 -> 5000 | M95: JazzCash | N95: Active | O95: 46230 | P95: =LEFT(A95,3) -> ORD | Q95: =RIGHT(A95,4) -> 1094 | R95: =FIND("-",A95) -> 4 | S95: =MID(A95,FIND("-",A95)+1,4) -> 1094
A96: ORD-1077 | B96: =CLEAN(TRIM(Raw_Data!B82)) -> Hira Iqbal | C96: hira.iqbal@hotmail.com | D96: 03626319061 | E96: =SUBSTITUTE(SUBSTITUTE(D96,"-","")," ","") -> 03626319061 | F96: =TRIM(PROPER(Raw_Data!E82)) -> Faisalabad | G96: =TRIM(PROPER(Raw_Data!F82)) -> Vacuum Cleaner | H96: Home Appliances | I96: 46253 | J96: 3 | K96: 1500 | L96: =J96*K96 -> 4500 | M96: Credit Card | N96: Active | O96: 46256 | P96: =LEFT(A96,3) -> ORD | Q96: =RIGHT(A96,4) -> 1077 | R96: =FIND("-",A96) -> 4 | S96: =MID(A96,FIND("-",A96)+1,4) -> 1077
A97: ORD-1053 | B97: =CLEAN(TRIM(Raw_Data!B56)) -> Zainab Aslam | C97: zainab.aslam@hotmail.com | D97: 0381 2913049 | E97: =SUBSTITUTE(SUBSTITUTE(D97,"-","")," ","") -> 03812913049 | F97: =TRIM(PROPER(Raw_Data!E56)) -> Multan | G97: =TRIM(PROPER(Raw_Data!F56)) -> Led Tv | H97: Electronics | I97: 46213 | J97: 1 | K97: 4000 | L97: =J97*K97 -> 4000 | M97: JazzCash | N97: InActive | O97: 46220 | P97: =LEFT(A97,3) -> ORD | Q97: =RIGHT(A97,4) -> 1053 | R97: =FIND("-",A97) -> 4 | S97: =MID(A97,FIND("-",A97)+1,4) -> 1053
A98: ORD-1006 | B98: =CLEAN(TRIM(Raw_Data!B7)) -> Kashif Anwar | C98: kashif.anwar@gmail.com | D98: 0377-4337174 | E98: =SUBSTITUTE(SUBSTITUTE(D98,"-","")," ","") -> 03774337174 | F98: =TRIM(PROPER(Raw_Data!E7)) -> Islamabad | G98: =TRIM(PROPER(Raw_Data!F7)) -> Microwave Oven | H98: =TRIM(PROPER(Raw_Data!G7)) -> Home Appliances | I98: 46227 | J98: 2 | K98: 1500 | L98: =J98*K98 -> 3000 | M98: Credit Card | N98: Active | O98: 46231 | P98: =LEFT(A98,3) -> ORD | Q98: =RIGHT(A98,4) -> 1006 | R98: =FIND("-",A98) -> 4 | S98: =MID(A98,FIND("-",A98)+1,4) -> 1006
A99: ORD-1015 | B99: =CLEAN(TRIM(Raw_Data!B16)) -> Junaid Khan | C99: junaid.khan@hotmail.com | D99: 03945163555 | E99: =SUBSTITUTE(SUBSTITUTE(D99,"-","")," ","") -> 03945163555 | F99: =TRIM(PROPER(Raw_Data!E16)) -> Karachi | G99: =TRIM(PROPER(Raw_Data!F16)) -> Blender | H99: =TRIM(PROPER(Raw_Data!G16)) -> Home Appliances | I99: 46254 | J99: 2 | K99: 1500 | L99: =J99*K99 -> 3000 | M99: Credit Card | N99: Active | O99: 46257 | P99: =LEFT(A99,3) -> ORD | Q99: =RIGHT(A99,4) -> 1015 | R99: =FIND("-",A99) -> 4 | S99: =MID(A99,FIND("-",A99)+1,4) -> 1015
A100: ORD-1075 | B100: =CLEAN(TRIM(Raw_Data!B60)) -> Mahnoor Qureshi | C100: mahnoor.qureshi@gmail.com | D100: 0399 4817541 | E100: =SUBSTITUTE(SUBSTITUTE(D100,"-","")," ","") -> 03994817541 | F100: =TRIM(PROPER(Raw_Data!E60)) -> Sialkot | G100: =TRIM(PROPER(Raw_Data!F60)) -> Water Dispenser | H100: Home Appliances | I100: 46248 | J100: 2 | K100: 1500 | L100: =J100*K100 -> 3000 | M100: JazzCash | N100: Active | O100: 46250 | P100: =LEFT(A100,3) -> ORD | Q100: =RIGHT(A100,4) -> 1075 | R100: =FIND("-",A100) -> 4 | S100: =MID(A100,FIND("-",A100)+1,4) -> 1075
...
